[
    {
        "type": "arrival",
        "status": "landed",
        "departure": {
            "iataCode": "ace",
            "icaoCode": "gcrr",
            "terminal": "1",
            "gate": "7",
            "delay": 10,
            "scheduledTime": "2023-08-19t20:55:00.000",
            "estimatedTime": "2023-08-19t20:55:00.000",
            "actualTime": "2023-08-19t21:05:00.000",
            "estimatedRunway": "2023-08-19t21:05:00.000",
            "actualRunway": "2023-08-19t21:05:00.000"
        },
        "arrival": {
            "iataCode": "lba",
            "icaoCode": "egnm",
            "scheduledTime": "2023-08-20t01:15:00.000",
            "estimatedTime": "2023-08-20t00:49:00.000",
            "actualTime": "2023-08-20t00:48:00.000",
            "estimatedRunway": "2023-08-20t00:48:00.000",
            "actualRunway": "2023-08-20t00:48:00.000"
        },
        "airline": {
            "name": "jet2",
            "iataCode": "ls",
            "icaoCode": "exs"
        },
        "flight": {
            "number": "218",
            "iataNumber": "ls218",
            "icaoNumber": "exs218"
        }
    },
    {
        "type": "arrival",
        "status": "active",
        "departure": {
            "iataCode": "fue",
            "icaoCode": "gcfv",
            "delay": 35,
            "scheduledTime": "2023-08-19t21:05:00.000",
            "estimatedTime": "2023-08-19t21:20:00.000",
            "actualTime": "2023-08-19t21:39:00.000",
            "estimatedRunway": "2023-08-19t21:39:00.000",
            "actualRunway": "2023-08-19t21:39:00.000"
        },
        "arrival": {
            "iataCode": "lba",
            "icaoCode": "egnm",
            "scheduledTime": "2023-08-20t01:25:00.000",
            "estimatedTime": "2023-08-20t01:16:00.000"
        },
        "airline": {
            "name": "jet2",
            "iataCode": "ls",
            "icaoCode": "exs"
        },
        "flight": {
            "number": "250",
            "iataNumber": "ls250",
            "icaoNumber": "exs250"
        }
    },
    {
        "type": "arrival",
        "status": "landed",
        "departure": {
            "iataCode": "pmi",
            "icaoCode": "lepa",
            "gate": "a5",
            "scheduledTime": "2023-08-19t23:55:00.000",
            "estimatedTime": "2023-08-19t23:55:00.000",
            "actualTime": "2023-08-19t23:55:00.000",
            "estimatedRunway": "2023-08-19t23:55:00.000",
            "actualRunway": "2023-08-19t23:55:00.000"
        },
        "arrival": {
            "iataCode": "lba",
            "icaoCode": "egnm",
            "scheduledTime": "2023-08-20t01:45:00.000",
            "estimatedTime": "2023-08-20t01:12:00.000",
            "actualTime": "2023-08-20t01:11:00.000",
            "estimatedRunway": "2023-08-20t01:11:00.000",
            "actualRunway": "2023-08-20t01:11:00.000"
        },
        "airline": {
            "name": "jet2",
            "iataCode": "ls",
            "icaoCode": "exs"
        },
        "flight": {
            "number": "228",
            "iataNumber": "ls228",
            "icaoNumber": "exs228"
        }
    },
    {
        "type": "arrival",
        "status": "landed",
        "departure": {
            "iataCode": "alc",
            "icaoCode": "leal",
            "gate": "130",
            "delay": 17,
            "scheduledTime": "2023-08-19t23:55:00.000",
            "estimatedTime": "2023-08-19t23:55:00.000",
            "actualTime": "2023-08-20t00:12:00.000",
            "estimatedRunway": "2023-08-20t00:12:00.000",
            "actualRunway": "2023-08-20t00:12:00.000"
        },
        "arrival": {
            "iataCode": "lba",
            "icaoCode": "egnm",
            "scheduledTime": "2023-08-20t01:55:00.000",
            "estimatedTime": "2023-08-20t01:36:00.000",
            "actualTime": "2023-08-20t01:37:00.000",
            "estimatedRunway": "2023-08-20t01:37:00.000",
            "actualRunway": "2023-08-20t01:37:00.000"
        },
        "airline": {
            "name": "jet2",
            "iataCode": "ls",
            "icaoCode": "exs"
        },
        "flight": {
            "number": "274",
            "iataNumber": "ls274",
            "icaoNumber": "exs274"
        }
    },
    {
        "type": "arrival",
        "status": "landed",
        "departure": {
            "iataCode": "dlm",
            "icaoCode": "ltbs",
            "terminal": "i",
            "gate": "35",
            "delay": 17,
            "scheduledTime": "2023-08-19t23:55:00.000",
            "estimatedTime": "2023-08-20t00:05:00.000",
            "actualTime": "2023-08-20t00:11:00.000",
            "estimatedRunway": "2023-08-20t00:11:00.000",
            "actualRunway": "2023-08-20t00:11:00.000"
        },
        "arrival": {
            "iataCode": "lba",
            "icaoCode": "egnm",
            "scheduledTime": "2023-08-20t02:25:00.000",
            "estimatedTime": "2023-08-20t02:18:00.000",
            "actualTime": "2023-08-20t02:18:00.000",
            "estimatedRunway": "2023-08-20t02:18:00.000",
            "actualRunway": "2023-08-20t02:18:00.000"
        },
        "airline": {
            "name": "jet2",
            "iataCode": "ls",
            "icaoCode": "exs"
        },
        "flight": {
            "number": "476",
            "iataNumber": "ls476",
            "icaoNumber": "exs476"
        }
    },
    {
        "type": "arrival",
        "status": "landed",
        "departure": {
            "iataCode": "pfo",
            "icaoCode": "lcph",
            "delay": 24,
            "scheduledTime": "2023-08-19t23:25:00.000",
            "estimatedTime": "2023-08-19t23:35:00.000",
            "actualTime": "2023-08-19t23:48:00.000",
            "estimatedRunway": "2023-08-19t23:48:00.000",
            "actualRunway": "2023-08-19t23:48:00.000"
        },
        "arrival": {
            "iataCode": "lba",
            "icaoCode": "egnm",
            "scheduledTime": "2023-08-20t02:30:00.000",
            "estimatedTime": "2023-08-20t02:25:00.000",
            "actualTime": "2023-08-20t02:22:00.000",
            "estimatedRunway": "2023-08-20t02:22:00.000",
            "actualRunway": "2023-08-20t02:22:00.000"
        },
        "airline": {
            "name": "jet2",
            "iataCode": "ls",
            "icaoCode": "exs"
        },
        "flight": {
            "number": "406",
            "iataNumber": "ls406",
            "icaoNumber": "exs406"
        }
    },
    {
        "type": "arrival",
        "status": "active",
        "departure": {
            "iataCode": "lpa",
            "icaoCode": "gclp",
            "delay": 22,
            "scheduledTime": "2023-08-19t22:30:00.000",
            "estimatedTime": "2023-08-19t22:30:00.000",
            "actualTime": "2023-08-19t22:52:00.000",
            "estimatedRunway": "2023-08-19t22:52:00.000",
            "actualRunway": "2023-08-19t22:52:00.000"
        },
        "arrival": {
            "iataCode": "lba",
            "icaoCode": "egnm",
            "scheduledTime": "2023-08-20t02:55:00.000",
            "estimatedTime": "2023-08-20t02:49:00.000"
        },
        "airline": {
            "name": "jet2",
            "iataCode": "ls",
            "icaoCode": "exs"
        },
        "flight": {
            "number": "478",
            "iataNumber": "ls478",
            "icaoNumber": "exs478"
        }
    },
    {
        "type": "arrival",
        "status": "landed",
        "departure": {
            "iataCode": "ayt",
            "icaoCode": "ltai",
            "terminal": "2",
            "gate": "220",
            "delay": 50,
            "scheduledTime": "2023-08-20t00:30:00.000",
            "estimatedTime": "2023-08-20t00:30:00.000",
            "actualTime": "2023-08-20t01:19:00.000",
            "estimatedRunway": "2023-08-20t01:19:00.000",
            "actualRunway": "2023-08-20t01:19:00.000"
        },
        "arrival": {
            "iataCode": "lba",
            "icaoCode": "egnm",
            "delay": 24,
            "scheduledTime": "2023-08-20t03:10:00.000",
            "estimatedTime": "2023-08-20t03:40:00.000",
            "actualTime": "2023-08-20t03:34:00.000",
            "estimatedRunway": "2023-08-20t03:34:00.000",
            "actualRunway": "2023-08-20t03:34:00.000"
        },
        "airline": {
            "name": "jet2",
            "iataCode": "ls",
            "icaoCode": "exs"
        },
        "flight": {
            "number": "3214",
            "iataNumber": "ls3214",
            "icaoNumber": "exs3214"
        }
    },
    {
        "type": "arrival",
        "status": "landed",
        "departure": {
            "iataCode": "tfs",
            "icaoCode": "gcts",
            "delay": 18,
            "scheduledTime": "2023-08-19t22:50:00.000",
            "estimatedTime": "2023-08-19t23:10:00.000",
            "actualTime": "2023-08-19t23:08:00.000",
            "estimatedRunway": "2023-08-19t23:08:00.000",
            "actualRunway": "2023-08-19t23:08:00.000"
        },
        "arrival": {
            "iataCode": "lba",
            "icaoCode": "egnm",
            "scheduledTime": "2023-08-20t03:25:00.000",
            "estimatedTime": "2023-08-20t02:57:00.000",
            "actualTime": "2023-08-20t02:56:00.000",
            "estimatedRunway": "2023-08-20t02:56:00.000",
            "actualRunway": "2023-08-20t02:56:00.000"
        },
        "airline": {
            "name": "jet2",
            "iataCode": "ls",
            "icaoCode": "exs"
        },
        "flight": {
            "number": "224",
            "iataNumber": "ls224",
            "icaoNumber": "exs224"
        }
    },
    {
        "type": "arrival",
        "status": "landed",
        "departure": {
            "iataCode": "bhd",
            "icaoCode": "egac",
            "delay": 6,
            "scheduledTime": "2023-08-20t06:50:00.000",
            "estimatedTime": "2023-08-20t06:50:00.000",
            "actualTime": "2023-08-20t06:56:00.000",
            "estimatedRunway": "2023-08-20t06:56:00.000",
            "actualRunway": "2023-08-20t06:56:00.000"
        },
        "arrival": {
            "iataCode": "lba",
            "icaoCode": "egnm",
            "scheduledTime": "2023-08-20t08:00:00.000",
            "estimatedTime": "2023-08-20t07:47:00.000",
            "actualTime": "2023-08-20t07:44:00.000",
            "estimatedRunway": "2023-08-20t07:44:00.000",
            "actualRunway": "2023-08-20t07:44:00.000"
        },
        "airline": {
            "name": "british airways",
            "iataCode": "ba",
            "icaoCode": "baw"
        },
        "flight": {
            "number": "8854",
            "iataNumber": "ba8854",
            "icaoNumber": "baw8854"
        },
        "codeshared": {
            "airline": {
                "name": "aer lingus",
                "iataCode": "ei",
                "icaoCode": "ein"
            },
            "flight": {
                "number": "3670",
                "iataNumber": "ei3670",
                "icaoNumber": "ein3670"
            }
        }
    },
    {
        "type": "arrival",
        "status": "landed",
        "departure": {
            "iataCode": "bhd",
            "icaoCode": "egac",
            "delay": 6,
            "scheduledTime": "2023-08-20t06:50:00.000",
            "estimatedTime": "2023-08-20t06:50:00.000",
            "actualTime": "2023-08-20t06:56:00.000",
            "estimatedRunway": "2023-08-20t06:56:00.000",
            "actualRunway": "2023-08-20t06:56:00.000"
        },
        "arrival": {
            "iataCode": "lba",
            "icaoCode": "egnm",
            "scheduledTime": "2023-08-20t08:00:00.000",
            "estimatedTime": "2023-08-20t07:47:00.000",
            "actualTime": "2023-08-20t07:44:00.000",
            "estimatedRunway": "2023-08-20t07:44:00.000",
            "actualRunway": "2023-08-20t07:44:00.000"
        },
        "airline": {
            "name": "aer lingus",
            "iataCode": "ei",
            "icaoCode": "ein"
        },
        "flight": {
            "number": "3670",
            "iataNumber": "ei3670",
            "icaoNumber": "ein3670"
        }
    },
    {
        "type": "arrival",
        "status": "landed",
        "departure": {
            "iataCode": "alc",
            "icaoCode": "leal",
            "gate": "50",
            "delay": 7,
            "scheduledTime": "2023-08-20t06:20:00.000",
            "estimatedTime": "2023-08-20t06:31:00.000",
            "actualTime": "2023-08-20t06:27:00.000",
            "estimatedRunway": "2023-08-20t06:27:00.000",
            "actualRunway": "2023-08-20t06:27:00.000"
        },
        "arrival": {
            "iataCode": "lba",
            "icaoCode": "egnm",
            "gate": "b19",
            "scheduledTime": "2023-08-20t08:05:00.000",
            "estimatedTime": "2023-08-20t07:51:00.000",
            "actualTime": "2023-08-20t07:50:00.000",
            "estimatedRunway": "2023-08-20t07:50:00.000",
            "actualRunway": "2023-08-20t07:50:00.000"
        },
        "airline": {
            "name": "ryanair",
            "iataCode": "fr",
            "icaoCode": "ryr"
        },
        "flight": {
            "number": "9078",
            "iataNumber": "fr9078",
            "icaoNumber": "ryr9078"
        }
    },
    {
        "type": "arrival",
        "status": "active",
        "departure": {
            "iataCode": "dub",
            "icaoCode": "eidw",
            "terminal": "2",
            "gate": "334",
            "delay": 30,
            "scheduledTime": "2023-08-20t07:20:00.000",
            "estimatedTime": "2023-08-20t07:48:00.000",
            "actualTime": "2023-08-20t07:50:00.000",
            "estimatedRunway": "2023-08-20t07:50:00.000",
            "actualRunway": "2023-08-20t07:50:00.000"
        },
        "arrival": {
            "iataCode": "lba",
            "icaoCode": "egnm",
            "delay": 6,
            "scheduledTime": "2023-08-20t08:30:00.000",
            "estimatedTime": "2023-08-20t08:35:00.000"
        },
        "airline": {
            "name": "british airways",
            "iataCode": "ba",
            "icaoCode": "baw"
        },
        "flight": {
            "number": "8960",
            "iataNumber": "ba8960",
            "icaoNumber": "baw8960"
        },
        "codeshared": {
            "airline": {
                "name": "aer lingus",
                "iataCode": "ei",
                "icaoCode": "ein"
            },
            "flight": {
                "number": "3390",
                "iataNumber": "ei3390",
                "icaoNumber": "ein3390"
            }
        }
    },
    {
        "type": "arrival",
        "status": "active",
        "departure": {
            "iataCode": "dub",
            "icaoCode": "eidw",
            "terminal": "2",
            "gate": "334",
            "delay": 30,
            "scheduledTime": "2023-08-20t07:20:00.000",
            "estimatedTime": "2023-08-20t07:48:00.000",
            "actualTime": "2023-08-20t07:50:00.000",
            "estimatedRunway": "2023-08-20t07:50:00.000",
            "actualRunway": "2023-08-20t07:50:00.000"
        },
        "arrival": {
            "iataCode": "lba",
            "icaoCode": "egnm",
            "delay": 6,
            "scheduledTime": "2023-08-20t08:30:00.000",
            "estimatedTime": "2023-08-20t08:35:00.000"
        },
        "airline": {
            "name": "aer lingus",
            "iataCode": "ei",
            "icaoCode": "ein"
        },
        "flight": {
            "number": "3390",
            "iataNumber": "ei3390",
            "icaoNumber": "ein3390"
        }
    },
    {
        "type": "arrival",
        "status": "scheduled",
        "departure": {
            "iataCode": "ams",
            "icaoCode": "eham",
            "terminal": "2",
            "gate": "d6",
            "delay": 17,
            "scheduledTime": "2023-08-20t09:20:00.000",
            "estimatedTime": "2023-08-20t09:37:00.000"
        },
        "arrival": {
            "iataCode": "lba",
            "icaoCode": "egnm",
            "scheduledTime": "2023-08-20t09:30:00.000"
        },
        "airline": {
            "name": "air france",
            "iataCode": "af",
            "icaoCode": "afr"
        },
        "flight": {
            "number": "3245",
            "iataNumber": "af3245",
            "icaoNumber": "afr3245"
        },
        "codeshared": {
            "airline": {
                "name": "klm",
                "iataCode": "kl",
                "icaoCode": "klm"
            },
            "flight": {
                "number": "1541",
                "iataNumber": "kl1541",
                "icaoNumber": "klm1541"
            }
        }
    },
    {
        "type": "arrival",
        "status": "scheduled",
        "departure": {
            "iataCode": "ams",
            "icaoCode": "eham",
            "terminal": "2",
            "gate": "d6",
            "delay": 17,
            "scheduledTime": "2023-08-20t09:20:00.000",
            "estimatedTime": "2023-08-20t09:37:00.000"
        },
        "arrival": {
            "iataCode": "lba",
            "icaoCode": "egnm",
            "scheduledTime": "2023-08-20t09:30:00.000"
        },
        "airline": {
            "name": "delta air lines",
            "iataCode": "dl",
            "icaoCode": "dal"
        },
        "flight": {
            "number": "9638",
            "iataNumber": "dl9638",
            "icaoNumber": "dal9638"
        },
        "codeshared": {
            "airline": {
                "name": "klm",
                "iataCode": "kl",
                "icaoCode": "klm"
            },
            "flight": {
                "number": "1541",
                "iataNumber": "kl1541",
                "icaoNumber": "klm1541"
            }
        }
    },
    {
        "type": "arrival",
        "status": "scheduled",
        "departure": {
            "iataCode": "ams",
            "icaoCode": "eham",
            "terminal": "2",
            "gate": "d6",
            "delay": 17,
            "scheduledTime": "2023-08-20t09:20:00.000",
            "estimatedTime": "2023-08-20t09:37:00.000"
        },
        "arrival": {
            "iataCode": "lba",
            "icaoCode": "egnm",
            "scheduledTime": "2023-08-20t09:30:00.000"
        },
        "airline": {
            "name": "kenya airways",
            "iataCode": "kq",
            "icaoCode": "kqa"
        },
        "flight": {
            "number": "1541",
            "iataNumber": "kq1541",
            "icaoNumber": "kqa1541"
        },
        "codeshared": {
            "airline": {
                "name": "klm",
                "iataCode": "kl",
                "icaoCode": "klm"
            },
            "flight": {
                "number": "1541",
                "iataNumber": "kl1541",
                "icaoNumber": "klm1541"
            }
        }
    },
    {
        "type": "arrival",
        "status": "scheduled",
        "departure": {
            "iataCode": "ams",
            "icaoCode": "eham",
            "terminal": "2",
            "gate": "d6",
            "delay": 17,
            "scheduledTime": "2023-08-20t09:20:00.000",
            "estimatedTime": "2023-08-20t09:37:00.000"
        },
        "arrival": {
            "iataCode": "lba",
            "icaoCode": "egnm",
            "scheduledTime": "2023-08-20t09:30:00.000"
        },
        "airline": {
            "name": "xiamen airlines",
            "iataCode": "mf",
            "icaoCode": "cxa"
        },
        "flight": {
            "number": "9161",
            "iataNumber": "mf9161",
            "icaoNumber": "cxa9161"
        },
        "codeshared": {
            "airline": {
                "name": "klm",
                "iataCode": "kl",
                "icaoCode": "klm"
            },
            "flight": {
                "number": "1541",
                "iataNumber": "kl1541",
                "icaoNumber": "klm1541"
            }
        }
    },
    {
        "type": "arrival",
        "status": "scheduled",
        "departure": {
            "iataCode": "ams",
            "icaoCode": "eham",
            "terminal": "2",
            "gate": "d6",
            "delay": 17,
            "scheduledTime": "2023-08-20t09:20:00.000",
            "estimatedTime": "2023-08-20t09:37:00.000"
        },
        "arrival": {
            "iataCode": "lba",
            "icaoCode": "egnm",
            "scheduledTime": "2023-08-20t09:30:00.000"
        },
        "airline": {
            "name": "virgin atlantic",
            "iataCode": "vs",
            "icaoCode": "vir"
        },
        "flight": {
            "number": "6980",
            "iataNumber": "vs6980",
            "icaoNumber": "vir6980"
        },
        "codeshared": {
            "airline": {
                "name": "klm",
                "iataCode": "kl",
                "icaoCode": "klm"
            },
            "flight": {
                "number": "1541",
                "iataNumber": "kl1541",
                "icaoNumber": "klm1541"
            }
        }
    },
    {
        "type": "arrival",
        "status": "scheduled",
        "departure": {
            "iataCode": "ams",
            "icaoCode": "eham",
            "terminal": "2",
            "gate": "d6",
            "delay": 17,
            "scheduledTime": "2023-08-20t09:20:00.000",
            "estimatedTime": "2023-08-20t09:37:00.000"
        },
        "arrival": {
            "iataCode": "lba",
            "icaoCode": "egnm",
            "scheduledTime": "2023-08-20t09:30:00.000"
        },
        "airline": {
            "name": "klm",
            "iataCode": "kl",
            "icaoCode": "klm"
        },
        "flight": {
            "number": "1541",
            "iataNumber": "kl1541",
            "icaoNumber": "klm1541"
        }
    },
    {
        "type": "arrival",
        "status": "scheduled",
        "departure": {
            "iataCode": "dub",
            "icaoCode": "eidw",
            "terminal": "1",
            "gate": "102",
            "scheduledTime": "2023-08-20t08:35:00.000",
            "estimatedTime": "2023-08-20t08:35:00.000"
        },
        "arrival": {
            "iataCode": "lba",
            "icaoCode": "egnm",
            "gate": "102",
            "scheduledTime": "2023-08-20t09:40:00.000"
        },
        "airline": {
            "name": "ryanair",
            "iataCode": "fr",
            "icaoCode": "ryr"
        },
        "flight": {
            "number": "152",
            "iataNumber": "fr152",
            "icaoNumber": "ryr152"
        }
    },
    {
        "type": "arrival",
        "status": "scheduled",
        "departure": {
            "iataCode": "dub",
            "icaoCode": "eidw",
            "terminal": "2",
            "gate": "337",
            "delay": 54,
            "scheduledTime": "2023-08-20t10:20:00.000",
            "estimatedTime": "2023-08-20t10:20:00.000",
            "actualTime": "2023-08-20t11:13:00.000",
            "estimatedRunway": "2023-08-20t11:13:00.000",
            "actualRunway": "2023-08-20t11:13:00.000"
        },
        "arrival": {
            "iataCode": "lba",
            "icaoCode": "egnm",
            "delay": 31,
            "scheduledTime": "2023-08-20t11:30:00.000",
            "estimatedTime": "2023-08-20t12:01:00.000"
        },
        "airline": {
            "name": "british airways",
            "iataCode": "ba",
            "icaoCode": "baw"
        },
        "flight": {
            "number": "8870",
            "iataNumber": "ba8870",
            "icaoNumber": "baw8870"
        },
        "codeshared": {
            "airline": {
                "name": "aer lingus",
                "iataCode": "ei",
                "icaoCode": "ein"
            },
            "flight": {
                "number": "3392",
                "iataNumber": "ei3392",
                "icaoNumber": "ein3392"
            }
        }
    },
    {
        "type": "arrival",
        "status": "scheduled",
        "departure": {
            "iataCode": "dub",
            "icaoCode": "eidw",
            "terminal": "2",
            "gate": "337",
            "delay": 54,
            "scheduledTime": "2023-08-20t10:20:00.000",
            "estimatedTime": "2023-08-20t10:20:00.000",
            "actualTime": "2023-08-20t11:13:00.000",
            "estimatedRunway": "2023-08-20t11:13:00.000",
            "actualRunway": "2023-08-20t11:13:00.000"
        },
        "arrival": {
            "iataCode": "lba",
            "icaoCode": "egnm",
            "delay": 31,
            "scheduledTime": "2023-08-20t11:30:00.000",
            "estimatedTime": "2023-08-20t12:01:00.000"
        },
        "airline": {
            "name": "aer lingus",
            "iataCode": "ei",
            "icaoCode": "ein"
        },
        "flight": {
            "number": "3392",
            "iataNumber": "ei3392",
            "icaoNumber": "ein3392"
        }
    },
    {
        "type": "arrival",
        "status": "landed",
        "departure": {
            "iataCode": "pgf",
            "icaoCode": "lfmp",
            "delay": 11,
            "scheduledTime": "2023-08-20t10:20:00.000",
            "estimatedTime": "2023-08-20t10:20:00.000",
            "actualTime": "2023-08-20t10:31:00.000",
            "estimatedRunway": "2023-08-20t10:31:00.000",
            "actualRunway": "2023-08-20t10:31:00.000"
        },
        "arrival": {
            "iataCode": "lba",
            "icaoCode": "egnm",
            "gate": "3",
            "scheduledTime": "2023-08-20t11:35:00.000",
            "actualTime": "2023-08-20t11:17:00.000",
            "estimatedRunway": "2023-08-20t11:17:00.000",
            "actualRunway": "2023-08-20t11:17:00.000"
        },
        "airline": {
            "name": "ryanair",
            "iataCode": "fr",
            "icaoCode": "ryr"
        },
        "flight": {
            "number": "9360",
            "iataNumber": "fr9360",
            "icaoNumber": "ryr9360"
        }
    },
    {
        "type": "arrival",
        "status": "landed",
        "departure": {
            "iataCode": "gro",
            "icaoCode": "lege",
            "terminal": "1",
            "gate": "3",
            "delay": 4,
            "scheduledTime": "2023-08-20t10:10:00.000",
            "estimatedTime": "2023-08-20t10:10:00.000",
            "actualTime": "2023-08-20t10:14:00.000",
            "estimatedRunway": "2023-08-20t10:14:00.000",
            "actualRunway": "2023-08-20t10:14:00.000"
        },
        "arrival": {
            "iataCode": "lba",
            "icaoCode": "egnm",
            "scheduledTime": "2023-08-20t11:40:00.000",
            "actualTime": "2023-08-20t11:14:00.000",
            "estimatedRunway": "2023-08-20t11:14:00.000",
            "actualRunway": "2023-08-20t11:14:00.000"
        },
        "airline": {
            "name": "jet2",
            "iataCode": "ls",
            "icaoCode": "exs"
        },
        "flight": {
            "number": "256",
            "iataNumber": "ls256",
            "icaoNumber": "exs256"
        }
    },
    {
        "type": "arrival",
        "status": "active",
        "departure": {
            "iataCode": "mah",
            "icaoCode": "lemh",
            "terminal": "ter1",
            "gate": "15",
            "delay": 12,
            "scheduledTime": "2023-08-20t10:50:00.000",
            "estimatedTime": "2023-08-20t11:00:00.000",
            "actualTime": "2023-08-20t11:02:00.000",
            "estimatedRunway": "2023-08-20t11:02:00.000",
            "actualRunway": "2023-08-20t11:02:00.000"
        },
        "arrival": {
            "iataCode": "lba",
            "icaoCode": "egnm",
            "scheduledTime": "2023-08-20t12:40:00.000",
            "estimatedTime": "2023-08-20t12:26:00.000"
        },
        "airline": {
            "name": "jet2",
            "iataCode": "ls",
            "icaoCode": "exs"
        },
        "flight": {
            "number": "376",
            "iataNumber": "ls376",
            "icaoNumber": "exs376"
        }
    },
    {
        "type": "arrival",
        "status": "landed",
        "departure": {
            "iataCode": "ibz",
            "icaoCode": "leib",
            "terminal": "1",
            "gate": "10",
            "delay": 28,
            "scheduledTime": "2023-08-20t11:20:00.000",
            "estimatedTime": "2023-08-20t11:20:00.000",
            "actualTime": "2023-08-20t11:48:00.000",
            "estimatedRunway": "2023-08-20t11:48:00.000",
            "actualRunway": "2023-08-20t11:48:00.000"
        },
        "arrival": {
            "iataCode": "lba",
            "icaoCode": "egnm",
            "scheduledTime": "2023-08-20t13:15:00.000",
            "estimatedTime": "2023-08-20t13:11:00.000",
            "actualTime": "2023-08-20t13:09:00.000",
            "estimatedRunway": "2023-08-20t13:09:00.000",
            "actualRunway": "2023-08-20t13:09:00.000"
        },
        "airline": {
            "name": "jet2",
            "iataCode": "ls",
            "icaoCode": "exs"
        },
        "flight": {
            "number": "198",
            "iataNumber": "ls198",
            "icaoNumber": "exs198"
        }
    },
    {
        "type": "arrival",
        "status": "landed",
        "departure": {
            "iataCode": "pmi",
            "icaoCode": "lepa",
            "gate": "a5",
            "delay": 44,
            "scheduledTime": "2023-08-20t11:35:00.000",
            "estimatedTime": "2023-08-20t11:35:00.000",
            "actualTime": "2023-08-20t12:18:00.000",
            "estimatedRunway": "2023-08-20t12:18:00.000",
            "actualRunway": "2023-08-20t12:18:00.000"
        },
        "arrival": {
            "iataCode": "lba",
            "icaoCode": "egnm",
            "delay": 8,
            "scheduledTime": "2023-08-20t13:25:00.000",
            "actualTime": "2023-08-20t13:32:00.000",
            "estimatedRunway": "2023-08-20t13:32:00.000",
            "actualRunway": "2023-08-20t13:32:00.000"
        },
        "airline": {
            "name": "jet2",
            "iataCode": "ls",
            "icaoCode": "exs"
        },
        "flight": {
            "number": "258",
            "iataNumber": "ls258",
            "icaoNumber": "exs258"
        }
    },
    {
        "type": "arrival",
        "status": "landed",
        "departure": {
            "iataCode": "rix",
            "icaoCode": "evra",
            "delay": 6,
            "scheduledTime": "2023-08-20t12:40:00.000",
            "estimatedTime": "2023-08-20t12:47:00.000",
            "actualTime": "2023-08-20t12:46:00.000",
            "estimatedRunway": "2023-08-20t12:46:00.000",
            "actualRunway": "2023-08-20t12:46:00.000"
        },
        "arrival": {
            "iataCode": "lba",
            "icaoCode": "egnm",
            "gate": "c11",
            "scheduledTime": "2023-08-20t13:30:00.000",
            "estimatedTime": "2023-08-20t13:11:00.000",
            "actualTime": "2023-08-20t13:25:00.000",
            "estimatedRunway": "2023-08-20t13:25:00.000",
            "actualRunway": "2023-08-20t13:25:00.000"
        },
        "airline": {
            "name": "ryanair",
            "iataCode": "fr",
            "icaoCode": "ryr"
        },
        "flight": {
            "number": "2483",
            "iataNumber": "fr2483",
            "icaoNumber": "ryr2483"
        }
    },
    {
        "type": "arrival",
        "status": "landed",
        "departure": {
            "iataCode": "alc",
            "icaoCode": "leal",
            "gate": "130",
            "delay": 12,
            "scheduledTime": "2023-08-20t11:55:00.000",
            "estimatedTime": "2023-08-20t11:55:00.000",
            "actualTime": "2023-08-20t12:07:00.000",
            "estimatedRunway": "2023-08-20t12:07:00.000",
            "actualRunway": "2023-08-20t12:07:00.000"
        },
        "arrival": {
            "iataCode": "lba",
            "icaoCode": "egnm",
            "scheduledTime": "2023-08-20t13:55:00.000",
            "estimatedTime": "2023-08-20t13:35:00.000",
            "actualTime": "2023-08-20t13:28:00.000",
            "estimatedRunway": "2023-08-20t13:28:00.000",
            "actualRunway": "2023-08-20t13:28:00.000"
        },
        "airline": {
            "name": "jet2",
            "iataCode": "ls",
            "icaoCode": "exs"
        },
        "flight": {
            "number": "272",
            "iataNumber": "ls272",
            "icaoNumber": "exs272"
        }
    },
    {
        "type": "arrival",
        "status": "landed",
        "departure": {
            "iataCode": "agp",
            "icaoCode": "lemg",
            "gate": "376",
            "delay": 27,
            "scheduledTime": "2023-08-20t12:05:00.000",
            "estimatedTime": "2023-08-20t12:23:00.000",
            "actualTime": "2023-08-20t12:31:00.000",
            "estimatedRunway": "2023-08-20t12:31:00.000",
            "actualRunway": "2023-08-20t12:31:00.000"
        },
        "arrival": {
            "iataCode": "lba",
            "icaoCode": "egnm",
            "scheduledTime": "2023-08-20t14:15:00.000",
            "estimatedTime": "2023-08-20t14:06:00.000",
            "actualTime": "2023-08-20t13:59:00.000",
            "estimatedRunway": "2023-08-20t13:59:00.000",
            "actualRunway": "2023-08-20t13:59:00.000"
        },
        "airline": {
            "name": "jet2",
            "iataCode": "ls",
            "icaoCode": "exs"
        },
        "flight": {
            "number": "186",
            "iataNumber": "ls186",
            "icaoNumber": "exs186"
        }
    },
    {
        "type": "arrival",
        "status": "landed",
        "departure": {
            "iataCode": "pmi",
            "icaoCode": "lepa",
            "gate": "a21",
            "delay": 31,
            "scheduledTime": "2023-08-20t12:35:00.000",
            "estimatedTime": "2023-08-20t12:48:00.000",
            "actualTime": "2023-08-20t13:05:00.000",
            "estimatedRunway": "2023-08-20t13:05:00.000",
            "actualRunway": "2023-08-20t13:05:00.000"
        },
        "arrival": {
            "iataCode": "lba",
            "icaoCode": "egnm",
            "scheduledTime": "2023-08-20t14:25:00.000",
            "estimatedTime": "2023-08-20t14:20:00.000",
            "actualTime": "2023-08-20t14:20:00.000",
            "estimatedRunway": "2023-08-20t14:20:00.000",
            "actualRunway": "2023-08-20t14:20:00.000"
        },
        "airline": {
            "name": "jet2",
            "iataCode": "ls",
            "icaoCode": "exs"
        },
        "flight": {
            "number": "230",
            "iataNumber": "ls230",
            "icaoNumber": "exs230"
        }
    },
    {
        "type": "arrival",
        "status": "landed",
        "departure": {
            "iataCode": "gdn",
            "icaoCode": "epgd",
            "delay": 15,
            "scheduledTime": "2023-08-20t13:30:00.000",
            "estimatedTime": "2023-08-20t13:44:00.000",
            "actualTime": "2023-08-20t13:45:00.000",
            "estimatedRunway": "2023-08-20t13:45:00.000",
            "actualRunway": "2023-08-20t13:45:00.000"
        },
        "arrival": {
            "iataCode": "lba",
            "icaoCode": "egnm",
            "gate": "29",
            "delay": 6,
            "scheduledTime": "2023-08-20t14:50:00.000",
            "estimatedTime": "2023-08-20t14:47:00.000",
            "actualTime": "2023-08-20t14:55:00.000",
            "estimatedRunway": "2023-08-20t14:55:00.000",
            "actualRunway": "2023-08-20t14:55:00.000"
        },
        "airline": {
            "name": "ryanair",
            "iataCode": "fr",
            "icaoCode": "ryr"
        },
        "flight": {
            "number": "1504",
            "iataNumber": "fr1504",
            "icaoNumber": "ryr1504"
        }
    },
    {
        "type": "arrival",
        "status": "landed",
        "departure": {
            "iataCode": "dub",
            "icaoCode": "eidw",
            "terminal": "1",
            "gate": "110",
            "delay": 11,
            "scheduledTime": "2023-08-20t13:50:00.000",
            "estimatedTime": "2023-08-20t13:50:00.000",
            "actualTime": "2023-08-20t14:01:00.000",
            "estimatedRunway": "2023-08-20t14:01:00.000",
            "actualRunway": "2023-08-20t14:01:00.000"
        },
        "arrival": {
            "iataCode": "lba",
            "icaoCode": "egnm",
            "gate": "110",
            "scheduledTime": "2023-08-20t14:55:00.000",
            "actualTime": "2023-08-20t14:37:00.000",
            "estimatedRunway": "2023-08-20t14:37:00.000",
            "actualRunway": "2023-08-20t14:37:00.000"
        },
        "airline": {
            "name": "ryanair",
            "iataCode": "fr",
            "icaoCode": "ryr"
        },
        "flight": {
            "number": "457",
            "iataNumber": "fr457",
            "icaoNumber": "ryr457"
        }
    },
    {
        "type": "arrival",
        "status": "landed",
        "departure": {
            "iataCode": "dbv",
            "icaoCode": "lddu",
            "delay": 7,
            "scheduledTime": "2023-08-20t13:00:00.000",
            "estimatedTime": "2023-08-20t13:10:00.000",
            "actualTime": "2023-08-20t13:06:00.000",
            "estimatedRunway": "2023-08-20t13:06:00.000",
            "actualRunway": "2023-08-20t13:06:00.000"
        },
        "arrival": {
            "iataCode": "lba",
            "icaoCode": "egnm",
            "scheduledTime": "2023-08-20t15:10:00.000",
            "estimatedTime": "2023-08-20t14:59:00.000",
            "actualTime": "2023-08-20t14:59:00.000",
            "estimatedRunway": "2023-08-20t14:59:00.000",
            "actualRunway": "2023-08-20t14:59:00.000"
        },
        "airline": {
            "name": "jet2",
            "iataCode": "ls",
            "icaoCode": "exs"
        },
        "flight": {
            "number": "440",
            "iataNumber": "ls440",
            "icaoNumber": "exs440"
        }
    },
    {
        "type": "arrival",
        "status": "landed",
        "departure": {
            "iataCode": "bhd",
            "icaoCode": "egac",
            "delay": 42,
            "scheduledTime": "2023-08-20t14:15:00.000",
            "estimatedTime": "2023-08-20t14:45:00.000",
            "actualTime": "2023-08-20t14:57:00.000",
            "estimatedRunway": "2023-08-20t14:57:00.000",
            "actualRunway": "2023-08-20t14:57:00.000"
        },
        "arrival": {
            "iataCode": "lba",
            "icaoCode": "egnm",
            "delay": 21,
            "scheduledTime": "2023-08-20t15:25:00.000",
            "actualTime": "2023-08-20t15:46:00.000",
            "estimatedRunway": "2023-08-20t15:46:00.000",
            "actualRunway": "2023-08-20t15:46:00.000"
        },
        "airline": {
            "name": "british airways",
            "iataCode": "ba",
            "icaoCode": "baw"
        },
        "flight": {
            "number": "8872",
            "iataNumber": "ba8872",
            "icaoNumber": "baw8872"
        },
        "codeshared": {
            "airline": {
                "name": "aer lingus",
                "iataCode": "ei",
                "icaoCode": "ein"
            },
            "flight": {
                "number": "3676",
                "iataNumber": "ei3676",
                "icaoNumber": "ein3676"
            }
        }
    },
    {
        "type": "arrival",
        "status": "landed",
        "departure": {
            "iataCode": "bhd",
            "icaoCode": "egac",
            "delay": 42,
            "scheduledTime": "2023-08-20t14:15:00.000",
            "estimatedTime": "2023-08-20t14:45:00.000",
            "actualTime": "2023-08-20t14:57:00.000",
            "estimatedRunway": "2023-08-20t14:57:00.000",
            "actualRunway": "2023-08-20t14:57:00.000"
        },
        "arrival": {
            "iataCode": "lba",
            "icaoCode": "egnm",
            "delay": 21,
            "scheduledTime": "2023-08-20t15:25:00.000",
            "actualTime": "2023-08-20t15:46:00.000",
            "estimatedRunway": "2023-08-20t15:46:00.000",
            "actualRunway": "2023-08-20t15:46:00.000"
        },
        "airline": {
            "name": "aer lingus",
            "iataCode": "ei",
            "icaoCode": "ein"
        },
        "flight": {
            "number": "3676",
            "iataNumber": "ei3676",
            "icaoNumber": "ein3676"
        }
    },
    {
        "type": "arrival",
        "status": "landed",
        "departure": {
            "iataCode": "her",
            "icaoCode": "lgir",
            "delay": 27,
            "scheduledTime": "2023-08-20t12:55:00.000",
            "estimatedTime": "2023-08-20t13:05:00.000",
            "actualTime": "2023-08-20t13:21:00.000",
            "estimatedRunway": "2023-08-20t13:21:00.000",
            "actualRunway": "2023-08-20t13:21:00.000"
        },
        "arrival": {
            "iataCode": "lba",
            "icaoCode": "egnm",
            "delay": 1,
            "scheduledTime": "2023-08-20t15:25:00.000",
            "estimatedTime": "2023-08-20t15:28:00.000",
            "actualTime": "2023-08-20t15:26:00.000",
            "estimatedRunway": "2023-08-20t15:26:00.000",
            "actualRunway": "2023-08-20t15:26:00.000"
        },
        "airline": {
            "name": "jet2",
            "iataCode": "ls",
            "icaoCode": "exs"
        },
        "flight": {
            "number": "444",
            "iataNumber": "ls444",
            "icaoNumber": "exs444"
        }
    },
    {
        "type": "arrival",
        "status": "landed",
        "departure": {
            "iataCode": "fao",
            "icaoCode": "lpfr",
            "delay": 7,
            "scheduledTime": "2023-08-20t12:25:00.000",
            "estimatedTime": "2023-08-20t12:35:00.000",
            "actualTime": "2023-08-20t12:31:00.000",
            "estimatedRunway": "2023-08-20t12:31:00.000",
            "actualRunway": "2023-08-20t12:31:00.000"
        },
        "arrival": {
            "iataCode": "lba",
            "icaoCode": "egnm",
            "scheduledTime": "2023-08-20t15:35:00.000",
            "estimatedTime": "2023-08-20t15:03:00.000",
            "actualTime": "2023-08-20t15:04:00.000",
            "estimatedRunway": "2023-08-20t15:04:00.000",
            "actualRunway": "2023-08-20t15:04:00.000"
        },
        "airline": {
            "name": "jet2",
            "iataCode": "ls",
            "icaoCode": "exs"
        },
        "flight": {
            "number": "252",
            "iataNumber": "ls252",
            "icaoNumber": "exs252"
        }
    },
    {
        "type": "arrival",
        "status": "landed",
        "departure": {
            "iataCode": "zth",
            "icaoCode": "lgza",
            "gate": "6",
            "delay": 18,
            "scheduledTime": "2023-08-20t13:45:00.000",
            "estimatedTime": "2023-08-20t13:49:00.000",
            "actualTime": "2023-08-20t14:02:00.000",
            "estimatedRunway": "2023-08-20t14:02:00.000",
            "actualRunway": "2023-08-20t14:02:00.000"
        },
        "arrival": {
            "iataCode": "lba",
            "icaoCode": "egnm",
            "scheduledTime": "2023-08-20t15:40:00.000",
            "estimatedTime": "2023-08-20t15:32:00.000",
            "actualTime": "2023-08-20t15:30:00.000",
            "estimatedRunway": "2023-08-20t15:30:00.000",
            "actualRunway": "2023-08-20t15:30:00.000"
        },
        "airline": {
            "name": "jet2",
            "iataCode": "ls",
            "icaoCode": "exs"
        },
        "flight": {
            "number": "448",
            "iataNumber": "ls448",
            "icaoNumber": "exs448"
        }
    },
    {
        "type": "arrival",
        "status": "scheduled",
        "departure": {
            "iataCode": "tfs",
            "icaoCode": "gcts",
            "delay": 45,
            "scheduledTime": "2023-08-20t11:30:00.000",
            "estimatedTime": "2023-08-20t11:44:00.000",
            "actualTime": "2023-08-20t12:15:00.000",
            "estimatedRunway": "2023-08-20t12:15:00.000",
            "actualRunway": "2023-08-20t12:15:00.000"
        },
        "arrival": {
            "iataCode": "lba",
            "icaoCode": "egnm",
            "gate": "c38",
            "delay": 19,
            "scheduledTime": "2023-08-20t15:45:00.000",
            "estimatedTime": "2023-08-20t16:04:00.000"
        },
        "airline": {
            "name": "ryanair",
            "iataCode": "fr",
            "icaoCode": "ryr"
        },
        "flight": {
            "number": "2493",
            "iataNumber": "fr2493",
            "icaoNumber": "ryr2493"
        }
    },
    {
        "type": "arrival",
        "status": "landed",
        "departure": {
            "iataCode": "fue",
            "icaoCode": "gcfv",
            "delay": 23,
            "scheduledTime": "2023-08-20t11:25:00.000",
            "estimatedTime": "2023-08-20t11:30:00.000",
            "actualTime": "2023-08-20t11:48:00.000",
            "estimatedRunway": "2023-08-20t11:48:00.000",
            "actualRunway": "2023-08-20t11:48:00.000"
        },
        "arrival": {
            "iataCode": "lba",
            "icaoCode": "egnm",
            "scheduledTime": "2023-08-20t15:45:00.000",
            "estimatedTime": "2023-08-20t15:32:00.000",
            "actualTime": "2023-08-20t15:36:00.000",
            "estimatedRunway": "2023-08-20t15:36:00.000",
            "actualRunway": "2023-08-20t15:36:00.000"
        },
        "airline": {
            "name": "jet2",
            "iataCode": "ls",
            "icaoCode": "exs"
        },
        "flight": {
            "number": "250",
            "iataNumber": "ls250",
            "icaoNumber": "exs250"
        }
    },
    {
        "type": "arrival",
        "status": "landed",
        "departure": {
            "iataCode": "fnc",
            "icaoCode": "lpma",
            "terminal": "t1",
            "delay": 1,
            "scheduledTime": "2023-08-20t11:50:00.000",
            "estimatedTime": "2023-08-20t11:55:00.000",
            "actualTime": "2023-08-20t11:51:00.000",
            "estimatedRunway": "2023-08-20t11:51:00.000",
            "actualRunway": "2023-08-20t11:51:00.000"
        },
        "arrival": {
            "iataCode": "lba",
            "icaoCode": "egnm",
            "scheduledTime": "2023-08-20t15:45:00.000",
            "estimatedTime": "2023-08-20t15:09:00.000",
            "actualTime": "2023-08-20t15:08:00.000",
            "estimatedRunway": "2023-08-20t15:08:00.000",
            "actualRunway": "2023-08-20t15:08:00.000"
        },
        "airline": {
            "name": "jet2",
            "iataCode": "ls",
            "icaoCode": "exs"
        },
        "flight": {
            "number": "390",
            "iataNumber": "ls390",
            "icaoNumber": "exs390"
        }
    },
    {
        "type": "arrival",
        "status": "active",
        "departure": {
            "iataCode": "cfu",
            "icaoCode": "lgkr",
            "gate": "05a",
            "delay": 18,
            "scheduledTime": "2023-08-20t14:20:00.000",
            "estimatedTime": "2023-08-20t14:35:00.000",
            "actualTime": "2023-08-20t14:38:00.000",
            "estimatedRunway": "2023-08-20t14:38:00.000",
            "actualRunway": "2023-08-20t14:38:00.000"
        },
        "arrival": {
            "iataCode": "lba",
            "icaoCode": "egnm",
            "scheduledTime": "2023-08-20t16:00:00.000",
            "estimatedTime": "2023-08-20t15:53:00.000"
        },
        "airline": {
            "name": "jet2",
            "iataCode": "ls",
            "icaoCode": "exs"
        },
        "flight": {
            "number": "260",
            "iataNumber": "ls260",
            "icaoNumber": "exs260"
        }
    },
    {
        "type": "arrival",
        "status": "scheduled",
        "departure": {
            "iataCode": "ams",
            "icaoCode": "eham",
            "terminal": "2",
            "gate": "d6",
            "delay": 13,
            "scheduledTime": "2023-08-20t16:35:00.000",
            "estimatedTime": "2023-08-20t16:48:00.000"
        },
        "arrival": {
            "iataCode": "lba",
            "icaoCode": "egnm",
            "scheduledTime": "2023-08-20t16:45:00.000"
        },
        "airline": {
            "name": "air france",
            "iataCode": "af",
            "icaoCode": "afr"
        },
        "flight": {
            "number": "8387",
            "iataNumber": "af8387",
            "icaoNumber": "afr8387"
        },
        "codeshared": {
            "airline": {
                "name": "klm",
                "iataCode": "kl",
                "icaoCode": "klm"
            },
            "flight": {
                "number": "1549",
                "iataNumber": "kl1549",
                "icaoNumber": "klm1549"
            }
        }
    },
    {
        "type": "arrival",
        "status": "scheduled",
        "departure": {
            "iataCode": "ams",
            "icaoCode": "eham",
            "terminal": "2",
            "gate": "d6",
            "delay": 13,
            "scheduledTime": "2023-08-20t16:35:00.000",
            "estimatedTime": "2023-08-20t16:48:00.000"
        },
        "arrival": {
            "iataCode": "lba",
            "icaoCode": "egnm",
            "scheduledTime": "2023-08-20t16:45:00.000"
        },
        "airline": {
            "name": "delta air lines",
            "iataCode": "dl",
            "icaoCode": "dal"
        },
        "flight": {
            "number": "9251",
            "iataNumber": "dl9251",
            "icaoNumber": "dal9251"
        },
        "codeshared": {
            "airline": {
                "name": "klm",
                "iataCode": "kl",
                "icaoCode": "klm"
            },
            "flight": {
                "number": "1549",
                "iataNumber": "kl1549",
                "icaoNumber": "klm1549"
            }
        }
    },
    {
        "type": "arrival",
        "status": "scheduled",
        "departure": {
            "iataCode": "ams",
            "icaoCode": "eham",
            "terminal": "2",
            "gate": "d6",
            "delay": 13,
            "scheduledTime": "2023-08-20t16:35:00.000",
            "estimatedTime": "2023-08-20t16:48:00.000"
        },
        "arrival": {
            "iataCode": "lba",
            "icaoCode": "egnm",
            "scheduledTime": "2023-08-20t16:45:00.000"
        },
        "airline": {
            "name": "gol",
            "iataCode": "g3",
            "icaoCode": "glo"
        },
        "flight": {
            "number": "5552",
            "iataNumber": "g35552",
            "icaoNumber": "glo5552"
        },
        "codeshared": {
            "airline": {
                "name": "klm",
                "iataCode": "kl",
                "icaoCode": "klm"
            },
            "flight": {
                "number": "1549",
                "iataNumber": "kl1549",
                "icaoNumber": "klm1549"
            }
        }
    },
    {
        "type": "arrival",
        "status": "scheduled",
        "departure": {
            "iataCode": "ams",
            "icaoCode": "eham",
            "terminal": "2",
            "gate": "d6",
            "delay": 13,
            "scheduledTime": "2023-08-20t16:35:00.000",
            "estimatedTime": "2023-08-20t16:48:00.000"
        },
        "arrival": {
            "iataCode": "lba",
            "icaoCode": "egnm",
            "scheduledTime": "2023-08-20t16:45:00.000"
        },
        "airline": {
            "name": "kenya airways",
            "iataCode": "kq",
            "icaoCode": "kqa"
        },
        "flight": {
            "number": "1549",
            "iataNumber": "kq1549",
            "icaoNumber": "kqa1549"
        },
        "codeshared": {
            "airline": {
                "name": "klm",
                "iataCode": "kl",
                "icaoCode": "klm"
            },
            "flight": {
                "number": "1549",
                "iataNumber": "kl1549",
                "icaoNumber": "klm1549"
            }
        }
    },
    {
        "type": "arrival",
        "status": "scheduled",
        "departure": {
            "iataCode": "ams",
            "icaoCode": "eham",
            "terminal": "2",
            "gate": "d6",
            "delay": 13,
            "scheduledTime": "2023-08-20t16:35:00.000",
            "estimatedTime": "2023-08-20t16:48:00.000"
        },
        "arrival": {
            "iataCode": "lba",
            "icaoCode": "egnm",
            "scheduledTime": "2023-08-20t16:45:00.000"
        },
        "airline": {
            "name": "xiamen airlines",
            "iataCode": "mf",
            "icaoCode": "cxa"
        },
        "flight": {
            "number": "9943",
            "iataNumber": "mf9943",
            "icaoNumber": "cxa9943"
        },
        "codeshared": {
            "airline": {
                "name": "klm",
                "iataCode": "kl",
                "icaoCode": "klm"
            },
            "flight": {
                "number": "1549",
                "iataNumber": "kl1549",
                "icaoNumber": "klm1549"
            }
        }
    },
    {
        "type": "arrival",
        "status": "scheduled",
        "departure": {
            "iataCode": "ams",
            "icaoCode": "eham",
            "terminal": "2",
            "gate": "d6",
            "delay": 13,
            "scheduledTime": "2023-08-20t16:35:00.000",
            "estimatedTime": "2023-08-20t16:48:00.000"
        },
        "arrival": {
            "iataCode": "lba",
            "icaoCode": "egnm",
            "scheduledTime": "2023-08-20t16:45:00.000"
        },
        "airline": {
            "name": "virgin atlantic",
            "iataCode": "vs",
            "icaoCode": "vir"
        },
        "flight": {
            "number": "6982",
            "iataNumber": "vs6982",
            "icaoNumber": "vir6982"
        },
        "codeshared": {
            "airline": {
                "name": "klm",
                "iataCode": "kl",
                "icaoCode": "klm"
            },
            "flight": {
                "number": "1549",
                "iataNumber": "kl1549",
                "icaoNumber": "klm1549"
            }
        }
    },
    {
        "type": "arrival",
        "status": "scheduled",
        "departure": {
            "iataCode": "ams",
            "icaoCode": "eham",
            "terminal": "2",
            "gate": "d6",
            "delay": 13,
            "scheduledTime": "2023-08-20t16:35:00.000",
            "estimatedTime": "2023-08-20t16:48:00.000"
        },
        "arrival": {
            "iataCode": "lba",
            "icaoCode": "egnm",
            "scheduledTime": "2023-08-20t16:45:00.000"
        },
        "airline": {
            "name": "klm",
            "iataCode": "kl",
            "icaoCode": "klm"
        },
        "flight": {
            "number": "1549",
            "iataNumber": "kl1549",
            "icaoNumber": "klm1549"
        }
    },
    {
        "type": "arrival",
        "status": "scheduled",
        "departure": {
            "iataCode": "otp",
            "icaoCode": "lrop",
            "delay": 170,
            "scheduledTime": "2023-08-20t15:10:00.000",
            "estimatedTime": "2023-08-20t18:00:00.000"
        },
        "arrival": {
            "iataCode": "lba",
            "icaoCode": "egnm",
            "scheduledTime": "2023-08-20t16:55:00.000"
        },
        "airline": {
            "name": "wizz air",
            "iataCode": "w6",
            "icaoCode": "wzz"
        },
        "flight": {
            "number": "3015",
            "iataNumber": "w63015",
            "icaoNumber": "wzz3015"
        }
    },
    {
        "type": "arrival",
        "status": "scheduled",
        "departure": {
            "iataCode": "cdg",
            "icaoCode": "lfpg",
            "terminal": "3",
            "gate": "4",
            "delay": 38,
            "scheduledTime": "2023-08-20t16:35:00.000",
            "estimatedTime": "2023-08-20t17:13:00.000"
        },
        "arrival": {
            "iataCode": "lba",
            "icaoCode": "egnm",
            "scheduledTime": "2023-08-20t17:05:00.000"
        },
        "airline": {
            "name": "jet2",
            "iataCode": "ls",
            "icaoCode": "exs"
        },
        "flight": {
            "number": "316",
            "iataNumber": "ls316",
            "icaoNumber": "exs316"
        }
    },
    {
        "type": "arrival",
        "status": "landed",
        "departure": {
            "iataCode": "jer",
            "icaoCode": "egjj",
            "delay": 19,
            "scheduledTime": "2023-08-20t15:55:00.000",
            "estimatedTime": "2023-08-20t16:05:00.000",
            "actualTime": "2023-08-20t16:13:00.000",
            "estimatedRunway": "2023-08-20t16:13:00.000",
            "actualRunway": "2023-08-20t16:13:00.000"
        },
        "arrival": {
            "iataCode": "lba",
            "icaoCode": "egnm",
            "scheduledTime": "2023-08-20t17:10:00.000",
            "actualTime": "2023-08-20t17:04:00.000",
            "estimatedRunway": "2023-08-20t17:04:00.000",
            "actualRunway": "2023-08-20t17:04:00.000"
        },
        "airline": {
            "name": "jet2",
            "iataCode": "ls",
            "icaoCode": "exs"
        },
        "flight": {
            "number": "176",
            "iataNumber": "ls176",
            "icaoNumber": "exs176"
        }
    },
    {
        "type": "arrival",
        "status": "landed",
        "departure": {
            "iataCode": "prg",
            "icaoCode": "lkpr",
            "terminal": "1",
            "gate": "a8",
            "delay": 10,
            "scheduledTime": "2023-08-20t16:30:00.000",
            "estimatedTime": "2023-08-20t16:42:00.000",
            "actualTime": "2023-08-20t16:39:00.000",
            "estimatedRunway": "2023-08-20t16:39:00.000",
            "actualRunway": "2023-08-20t16:39:00.000"
        },
        "arrival": {
            "iataCode": "lba",
            "icaoCode": "egnm",
            "baggage": "142",
            "scheduledTime": "2023-08-20t17:45:00.000",
            "estimatedTime": "2023-08-20t17:27:00.000",
            "actualTime": "2023-08-20t17:37:00.000",
            "estimatedRunway": "2023-08-20t17:37:00.000",
            "actualRunway": "2023-08-20t17:37:00.000"
        },
        "airline": {
            "name": "jet2",
            "iataCode": "ls",
            "icaoCode": "exs"
        },
        "flight": {
            "number": "196",
            "iataNumber": "ls196",
            "icaoNumber": "exs196"
        }
    },
    {
        "type": "arrival",
        "status": "landed",
        "departure": {
            "iataCode": "bfs",
            "icaoCode": "egaa",
            "delay": 9,
            "scheduledTime": "2023-08-20t17:00:00.000",
            "estimatedTime": "2023-08-20t17:00:00.000",
            "actualTime": "2023-08-20t17:08:00.000",
            "estimatedRunway": "2023-08-20t17:08:00.000",
            "actualRunway": "2023-08-20t17:08:00.000"
        },
        "arrival": {
            "iataCode": "lba",
            "icaoCode": "egnm",
            "scheduledTime": "2023-08-20t18:00:00.000",
            "actualTime": "2023-08-20t17:46:00.000",
            "estimatedRunway": "2023-08-20t17:46:00.000",
            "actualRunway": "2023-08-20t17:46:00.000"
        },
        "airline": {
            "name": "easyjet",
            "iataCode": "u2",
            "icaoCode": "ezy"
        },
        "flight": {
            "number": "49",
            "iataNumber": "u249",
            "icaoNumber": "ezy49"
        }
    },
    {
        "type": "arrival",
        "status": "landed",
        "departure": {
            "iataCode": "gro",
            "icaoCode": "lege",
            "terminal": "1",
            "gate": "5",
            "delay": 27,
            "scheduledTime": "2023-08-20t17:10:00.000",
            "estimatedTime": "2023-08-20t17:15:00.000",
            "actualTime": "2023-08-20t17:36:00.000",
            "estimatedRunway": "2023-08-20t17:36:00.000",
            "actualRunway": "2023-08-20t17:36:00.000"
        },
        "arrival": {
            "iataCode": "lba",
            "icaoCode": "egnm",
            "gate": "5",
            "scheduledTime": "2023-08-20t18:30:00.000",
            "estimatedTime": "2023-08-20t18:31:00.000",
            "actualTime": "2023-08-20t18:29:00.000",
            "estimatedRunway": "2023-08-20t18:29:00.000",
            "actualRunway": "2023-08-20t18:29:00.000"
        },
        "airline": {
            "name": "ryanair",
            "iataCode": "fr",
            "icaoCode": "ryr"
        },
        "flight": {
            "number": "2324",
            "iataNumber": "fr2324",
            "icaoNumber": "ryr2324"
        }
    },
    {
        "type": "arrival",
        "status": "landed",
        "departure": {
            "iataCode": "bhd",
            "icaoCode": "egac",
            "delay": 29,
            "scheduledTime": "2023-08-20t17:35:00.000",
            "estimatedTime": "2023-08-20t17:55:00.000",
            "actualTime": "2023-08-20t18:03:00.000",
            "estimatedRunway": "2023-08-20t18:03:00.000",
            "actualRunway": "2023-08-20t18:03:00.000"
        },
        "arrival": {
            "iataCode": "lba",
            "icaoCode": "egnm",
            "delay": 6,
            "scheduledTime": "2023-08-20t18:45:00.000",
            "estimatedTime": "2023-08-20t18:48:00.000",
            "actualTime": "2023-08-20t18:51:00.000",
            "estimatedRunway": "2023-08-20t18:51:00.000",
            "actualRunway": "2023-08-20t18:51:00.000"
        },
        "airline": {
            "name": "british airways",
            "iataCode": "ba",
            "icaoCode": "baw"
        },
        "flight": {
            "number": "8986",
            "iataNumber": "ba8986",
            "icaoNumber": "baw8986"
        },
        "codeshared": {
            "airline": {
                "name": "aer lingus",
                "iataCode": "ei",
                "icaoCode": "ein"
            },
            "flight": {
                "number": "3678",
                "iataNumber": "ei3678",
                "icaoNumber": "ein3678"
            }
        }
    },
    {
        "type": "arrival",
        "status": "landed",
        "departure": {
            "iataCode": "bhd",
            "icaoCode": "egac",
            "delay": 29,
            "scheduledTime": "2023-08-20t17:35:00.000",
            "estimatedTime": "2023-08-20t17:55:00.000",
            "actualTime": "2023-08-20t18:03:00.000",
            "estimatedRunway": "2023-08-20t18:03:00.000",
            "actualRunway": "2023-08-20t18:03:00.000"
        },
        "arrival": {
            "iataCode": "lba",
            "icaoCode": "egnm",
            "delay": 6,
            "scheduledTime": "2023-08-20t18:45:00.000",
            "estimatedTime": "2023-08-20t18:48:00.000",
            "actualTime": "2023-08-20t18:51:00.000",
            "estimatedRunway": "2023-08-20t18:51:00.000",
            "actualRunway": "2023-08-20t18:51:00.000"
        },
        "airline": {
            "name": "aer lingus",
            "iataCode": "ei",
            "icaoCode": "ein"
        },
        "flight": {
            "number": "3678",
            "iataNumber": "ei3678",
            "icaoNumber": "ein3678"
        }
    },
    {
        "type": "arrival",
        "status": "scheduled",
        "departure": {
            "iataCode": "dub",
            "icaoCode": "eidw",
            "terminal": "2",
            "gate": "332",
            "delay": 100,
            "scheduledTime": "2023-08-20t17:50:00.000",
            "estimatedTime": "2023-08-20t19:30:00.000"
        },
        "arrival": {
            "iataCode": "lba",
            "icaoCode": "egnm",
            "scheduledTime": "2023-08-20t19:05:00.000"
        },
        "airline": {
            "name": "british airways",
            "iataCode": "ba",
            "icaoCode": "baw"
        },
        "flight": {
            "number": "8962",
            "iataNumber": "ba8962",
            "icaoNumber": "baw8962"
        },
        "codeshared": {
            "airline": {
                "name": "aer lingus",
                "iataCode": "ei",
                "icaoCode": "ein"
            },
            "flight": {
                "number": "3394",
                "iataNumber": "ei3394",
                "icaoNumber": "ein3394"
            }
        }
    },
    {
        "type": "arrival",
        "status": "scheduled",
        "departure": {
            "iataCode": "dub",
            "icaoCode": "eidw",
            "terminal": "2",
            "gate": "332",
            "delay": 100,
            "scheduledTime": "2023-08-20t17:50:00.000",
            "estimatedTime": "2023-08-20t19:30:00.000"
        },
        "arrival": {
            "iataCode": "lba",
            "icaoCode": "egnm",
            "scheduledTime": "2023-08-20t19:05:00.000"
        },
        "airline": {
            "name": "aer lingus",
            "iataCode": "ei",
            "icaoCode": "ein"
        },
        "flight": {
            "number": "3394",
            "iataNumber": "ei3394",
            "icaoNumber": "ein3394"
        }
    },
    {
        "type": "arrival",
        "status": "landed",
        "departure": {
            "iataCode": "opo",
            "icaoCode": "lppr",
            "delay": 12,
            "scheduledTime": "2023-08-20t17:20:00.000",
            "estimatedTime": "2023-08-20t17:20:00.000",
            "actualTime": "2023-08-20t17:31:00.000",
            "estimatedRunway": "2023-08-20t17:31:00.000",
            "actualRunway": "2023-08-20t17:31:00.000"
        },
        "arrival": {
            "iataCode": "lba",
            "icaoCode": "egnm",
            "gate": "10",
            "scheduledTime": "2023-08-20t19:55:00.000",
            "estimatedTime": "2023-08-20t19:23:00.000",
            "actualTime": "2023-08-20t19:23:00.000",
            "estimatedRunway": "2023-08-20t19:23:00.000",
            "actualRunway": "2023-08-20t19:23:00.000"
        },
        "airline": {
            "name": "ryanair",
            "iataCode": "fr",
            "icaoCode": "ryr"
        },
        "flight": {
            "number": "2400",
            "iataNumber": "fr2400",
            "icaoNumber": "ryr2400"
        }
    },
    {
        "type": "arrival",
        "status": "active",
        "departure": {
            "iataCode": "nap",
            "icaoCode": "lirn",
            "delay": 38,
            "scheduledTime": "2023-08-20t20:20:00.000",
            "estimatedTime": "2023-08-20t20:25:00.000",
            "actualTime": "2023-08-20t20:58:00.000",
            "estimatedRunway": "2023-08-20t20:58:00.000",
            "actualRunway": "2023-08-20t20:58:00.000"
        },
        "arrival": {
            "iataCode": "lba",
            "icaoCode": "egnm",
            "delay": 9,
            "scheduledTime": "2023-08-20t22:30:00.000",
            "estimatedTime": "2023-08-20t22:38:00.000"
        },
        "airline": {
            "name": "jet2",
            "iataCode": "ls",
            "icaoCode": "exs"
        },
        "flight": {
            "number": "366",
            "iataNumber": "ls366",
            "icaoNumber": "exs366"
        }
    },
    {
        "type": "arrival",
        "status": "landed",
        "departure": {
            "iataCode": "agp",
            "icaoCode": "lemg",
            "gate": "363",
            "delay": 23,
            "scheduledTime": "2023-08-20t20:40:00.000",
            "estimatedTime": "2023-08-20t20:40:00.000",
            "actualTime": "2023-08-20t21:03:00.000",
            "estimatedRunway": "2023-08-20t21:03:00.000",
            "actualRunway": "2023-08-20t21:03:00.000"
        },
        "arrival": {
            "iataCode": "lba",
            "icaoCode": "egnm",
            "gate": "c33",
            "scheduledTime": "2023-08-20t22:40:00.000",
            "estimatedTime": "2023-08-20t22:39:00.000",
            "actualTime": "2023-08-20t22:30:00.000",
            "estimatedRunway": "2023-08-20t22:30:00.000",
            "actualRunway": "2023-08-20t22:30:00.000"
        },
        "airline": {
            "name": "ryanair",
            "iataCode": "fr",
            "icaoCode": "ryr"
        },
        "flight": {
            "number": "2447",
            "iataNumber": "fr2447",
            "icaoNumber": "ryr2447"
        }
    },
    {
        "type": "arrival",
        "status": "landed",
        "departure": {
            "iataCode": "dub",
            "icaoCode": "eidw",
            "terminal": "1",
            "gate": "111",
            "delay": 83,
            "scheduledTime": "2023-08-20t21:40:00.000",
            "estimatedTime": "2023-08-20t21:40:00.000",
            "actualTime": "2023-08-20t23:02:00.000",
            "estimatedRunway": "2023-08-20t23:02:00.000",
            "actualRunway": "2023-08-20t23:02:00.000"
        },
        "arrival": {
            "iataCode": "lba",
            "icaoCode": "egnm",
            "gate": "111",
            "delay": 52,
            "scheduledTime": "2023-08-20t22:45:00.000",
            "actualTime": "2023-08-20t23:37:00.000",
            "estimatedRunway": "2023-08-20t23:37:00.000",
            "actualRunway": "2023-08-20t23:37:00.000"
        },
        "airline": {
            "name": "ryanair",
            "iataCode": "fr",
            "icaoCode": "ryr"
        },
        "flight": {
            "number": "156",
            "iataNumber": "fr156",
            "icaoNumber": "ryr156"
        }
    },
    {
        "type": "arrival",
        "status": "landed",
        "departure": {
            "iataCode": "pmi",
            "icaoCode": "lepa",
            "gate": "a14",
            "delay": 58,
            "scheduledTime": "2023-08-20t21:05:00.000",
            "estimatedTime": "2023-08-20t21:27:00.000",
            "actualTime": "2023-08-20t22:03:00.000",
            "estimatedRunway": "2023-08-20t22:03:00.000",
            "actualRunway": "2023-08-20t22:03:00.000"
        },
        "arrival": {
            "iataCode": "lba",
            "icaoCode": "egnm",
            "gate": "a14",
            "delay": 29,
            "scheduledTime": "2023-08-20t22:45:00.000",
            "estimatedTime": "2023-08-20t23:17:00.000",
            "actualTime": "2023-08-20t23:14:00.000",
            "estimatedRunway": "2023-08-20t23:14:00.000",
            "actualRunway": "2023-08-20t23:14:00.000"
        },
        "airline": {
            "name": "ryanair",
            "iataCode": "fr",
            "icaoCode": "ryr"
        },
        "flight": {
            "number": "2311",
            "iataNumber": "fr2311",
            "icaoNumber": "ryr2311"
        }
    },
    {
        "type": "arrival",
        "status": "landed",
        "departure": {
            "iataCode": "ams",
            "icaoCode": "eham",
            "terminal": "2",
            "gate": "d6",
            "delay": 11,
            "scheduledTime": "2023-08-20t22:40:00.000",
            "estimatedTime": "2023-08-20t22:40:00.000",
            "actualTime": "2023-08-20t22:50:00.000",
            "estimatedRunway": "2023-08-20t22:50:00.000",
            "actualRunway": "2023-08-20t22:50:00.000"
        },
        "arrival": {
            "iataCode": "lba",
            "icaoCode": "egnm",
            "scheduledTime": "2023-08-20t22:50:00.000",
            "estimatedTime": "2023-08-20t22:44:00.000",
            "actualTime": "2023-08-20t22:44:00.000",
            "estimatedRunway": "2023-08-20t22:44:00.000",
            "actualRunway": "2023-08-20t22:44:00.000"
        },
        "airline": {
            "name": "air france",
            "iataCode": "af",
            "icaoCode": "afr"
        },
        "flight": {
            "number": "8381",
            "iataNumber": "af8381",
            "icaoNumber": "afr8381"
        },
        "codeshared": {
            "airline": {
                "name": "klm",
                "iataCode": "kl",
                "icaoCode": "klm"
            },
            "flight": {
                "number": "1551",
                "iataNumber": "kl1551",
                "icaoNumber": "klm1551"
            }
        }
    },
    {
        "type": "arrival",
        "status": "landed",
        "departure": {
            "iataCode": "ams",
            "icaoCode": "eham",
            "terminal": "2",
            "gate": "d6",
            "delay": 11,
            "scheduledTime": "2023-08-20t22:40:00.000",
            "estimatedTime": "2023-08-20t22:40:00.000",
            "actualTime": "2023-08-20t22:50:00.000",
            "estimatedRunway": "2023-08-20t22:50:00.000",
            "actualRunway": "2023-08-20t22:50:00.000"
        },
        "arrival": {
            "iataCode": "lba",
            "icaoCode": "egnm",
            "scheduledTime": "2023-08-20t22:50:00.000",
            "estimatedTime": "2023-08-20t22:44:00.000",
            "actualTime": "2023-08-20t22:44:00.000",
            "estimatedRunway": "2023-08-20t22:44:00.000",
            "actualRunway": "2023-08-20t22:44:00.000"
        },
        "airline": {
            "name": "alitalia",
            "iataCode": "az",
            "icaoCode": "aza"
        },
        "flight": {
            "number": "3804",
            "iataNumber": "az3804",
            "icaoNumber": "aza3804"
        },
        "codeshared": {
            "airline": {
                "name": "klm",
                "iataCode": "kl",
                "icaoCode": "klm"
            },
            "flight": {
                "number": "1551",
                "iataNumber": "kl1551",
                "icaoNumber": "klm1551"
            }
        }
    },
    {
        "type": "arrival",
        "status": "landed",
        "departure": {
            "iataCode": "ams",
            "icaoCode": "eham",
            "terminal": "2",
            "gate": "d6",
            "delay": 11,
            "scheduledTime": "2023-08-20t22:40:00.000",
            "estimatedTime": "2023-08-20t22:40:00.000",
            "actualTime": "2023-08-20t22:50:00.000",
            "estimatedRunway": "2023-08-20t22:50:00.000",
            "actualRunway": "2023-08-20t22:50:00.000"
        },
        "arrival": {
            "iataCode": "lba",
            "icaoCode": "egnm",
            "scheduledTime": "2023-08-20t22:50:00.000",
            "estimatedTime": "2023-08-20t22:44:00.000",
            "actualTime": "2023-08-20t22:44:00.000",
            "estimatedRunway": "2023-08-20t22:44:00.000",
            "actualRunway": "2023-08-20t22:44:00.000"
        },
        "airline": {
            "name": "kenya airways",
            "iataCode": "kq",
            "icaoCode": "kqa"
        },
        "flight": {
            "number": "1551",
            "iataNumber": "kq1551",
            "icaoNumber": "kqa1551"
        },
        "codeshared": {
            "airline": {
                "name": "klm",
                "iataCode": "kl",
                "icaoCode": "klm"
            },
            "flight": {
                "number": "1551",
                "iataNumber": "kl1551",
                "icaoNumber": "klm1551"
            }
        }
    },
    {
        "type": "arrival",
        "status": "landed",
        "departure": {
            "iataCode": "ams",
            "icaoCode": "eham",
            "terminal": "2",
            "gate": "d6",
            "delay": 11,
            "scheduledTime": "2023-08-20t22:40:00.000",
            "estimatedTime": "2023-08-20t22:40:00.000",
            "actualTime": "2023-08-20t22:50:00.000",
            "estimatedRunway": "2023-08-20t22:50:00.000",
            "actualRunway": "2023-08-20t22:50:00.000"
        },
        "arrival": {
            "iataCode": "lba",
            "icaoCode": "egnm",
            "scheduledTime": "2023-08-20t22:50:00.000",
            "estimatedTime": "2023-08-20t22:44:00.000",
            "actualTime": "2023-08-20t22:44:00.000",
            "estimatedRunway": "2023-08-20t22:44:00.000",
            "actualRunway": "2023-08-20t22:44:00.000"
        },
        "airline": {
            "name": "xiamen airlines",
            "iataCode": "mf",
            "icaoCode": "cxa"
        },
        "flight": {
            "number": "9793",
            "iataNumber": "mf9793",
            "icaoNumber": "cxa9793"
        },
        "codeshared": {
            "airline": {
                "name": "klm",
                "iataCode": "kl",
                "icaoCode": "klm"
            },
            "flight": {
                "number": "1551",
                "iataNumber": "kl1551",
                "icaoNumber": "klm1551"
            }
        }
    },
    {
        "type": "arrival",
        "status": "landed",
        "departure": {
            "iataCode": "ams",
            "icaoCode": "eham",
            "terminal": "2",
            "gate": "d6",
            "delay": 11,
            "scheduledTime": "2023-08-20t22:40:00.000",
            "estimatedTime": "2023-08-20t22:40:00.000",
            "actualTime": "2023-08-20t22:50:00.000",
            "estimatedRunway": "2023-08-20t22:50:00.000",
            "actualRunway": "2023-08-20t22:50:00.000"
        },
        "arrival": {
            "iataCode": "lba",
            "icaoCode": "egnm",
            "scheduledTime": "2023-08-20t22:50:00.000",
            "estimatedTime": "2023-08-20t22:44:00.000",
            "actualTime": "2023-08-20t22:44:00.000",
            "estimatedRunway": "2023-08-20t22:44:00.000",
            "actualRunway": "2023-08-20t22:44:00.000"
        },
        "airline": {
            "name": "virgin atlantic",
            "iataCode": "vs",
            "icaoCode": "vir"
        },
        "flight": {
            "number": "7058",
            "iataNumber": "vs7058",
            "icaoNumber": "vir7058"
        },
        "codeshared": {
            "airline": {
                "name": "klm",
                "iataCode": "kl",
                "icaoCode": "klm"
            },
            "flight": {
                "number": "1551",
                "iataNumber": "kl1551",
                "icaoNumber": "klm1551"
            }
        }
    },
    {
        "type": "arrival",
        "status": "landed",
        "departure": {
            "iataCode": "ams",
            "icaoCode": "eham",
            "terminal": "2",
            "gate": "d6",
            "delay": 11,
            "scheduledTime": "2023-08-20t22:40:00.000",
            "estimatedTime": "2023-08-20t22:40:00.000",
            "actualTime": "2023-08-20t22:50:00.000",
            "estimatedRunway": "2023-08-20t22:50:00.000",
            "actualRunway": "2023-08-20t22:50:00.000"
        },
        "arrival": {
            "iataCode": "lba",
            "icaoCode": "egnm",
            "scheduledTime": "2023-08-20t22:50:00.000",
            "estimatedTime": "2023-08-20t22:44:00.000",
            "actualTime": "2023-08-20t22:44:00.000",
            "estimatedRunway": "2023-08-20t22:44:00.000",
            "actualRunway": "2023-08-20t22:44:00.000"
        },
        "airline": {
            "name": "klm",
            "iataCode": "kl",
            "icaoCode": "klm"
        },
        "flight": {
            "number": "1551",
            "iataNumber": "kl1551",
            "icaoNumber": "klm1551"
        }
    },
    {
        "type": "arrival",
        "status": "landed",
        "departure": {
            "iataCode": "agp",
            "icaoCode": "lemg",
            "gate": "384",
            "delay": 23,
            "scheduledTime": "2023-08-20t20:50:00.000",
            "estimatedTime": "2023-08-20t21:00:00.000",
            "actualTime": "2023-08-20t21:13:00.000",
            "estimatedRunway": "2023-08-20t21:13:00.000",
            "actualRunway": "2023-08-20t21:13:00.000"
        },
        "arrival": {
            "iataCode": "lba",
            "icaoCode": "egnm",
            "scheduledTime": "2023-08-20t22:55:00.000",
            "estimatedTime": "2023-08-20t22:40:00.000",
            "actualTime": "2023-08-20t22:42:00.000",
            "estimatedRunway": "2023-08-20t22:42:00.000",
            "actualRunway": "2023-08-20t22:42:00.000"
        },
        "airline": {
            "name": "jet2",
            "iataCode": "ls",
            "icaoCode": "exs"
        },
        "flight": {
            "number": "266",
            "iataNumber": "ls266",
            "icaoNumber": "exs266"
        }
    },
    {
        "type": "arrival",
        "status": "landed",
        "departure": {
            "iataCode": "ace",
            "icaoCode": "gcrr",
            "terminal": "1",
            "gate": "5",
            "delay": 33,
            "scheduledTime": "2023-08-20t19:15:00.000",
            "estimatedTime": "2023-08-20t19:15:00.000",
            "actualTime": "2023-08-20t19:48:00.000",
            "estimatedRunway": "2023-08-20t19:48:00.000",
            "actualRunway": "2023-08-20t19:48:00.000"
        },
        "arrival": {
            "iataCode": "lba",
            "icaoCode": "egnm",
            "gate": "5",
            "delay": 1,
            "scheduledTime": "2023-08-20t23:20:00.000",
            "estimatedTime": "2023-08-20t23:26:00.000",
            "actualTime": "2023-08-20t23:20:00.000",
            "estimatedRunway": "2023-08-20t23:20:00.000",
            "actualRunway": "2023-08-20t23:20:00.000"
        },
        "airline": {
            "name": "ryanair",
            "iataCode": "fr",
            "icaoCode": "ryr"
        },
        "flight": {
            "number": "2047",
            "iataNumber": "fr2047",
            "icaoNumber": "ryr2047"
        }
    },
    {
        "type": "arrival",
        "status": "landed",
        "departure": {
            "iataCode": "fao",
            "icaoCode": "lpfr",
            "delay": 4,
            "scheduledTime": "2023-08-20t20:10:00.000",
            "estimatedTime": "2023-08-20t20:25:00.000",
            "actualTime": "2023-08-20t20:14:00.000",
            "estimatedRunway": "2023-08-20t20:14:00.000",
            "actualRunway": "2023-08-20t20:14:00.000"
        },
        "arrival": {
            "iataCode": "lba",
            "icaoCode": "egnm",
            "scheduledTime": "2023-08-20t23:20:00.000",
            "actualTime": "2023-08-20t22:35:00.000",
            "estimatedRunway": "2023-08-20t22:35:00.000",
            "actualRunway": "2023-08-20t22:35:00.000"
        },
        "airline": {
            "name": "jet2",
            "iataCode": "ls",
            "icaoCode": "exs"
        },
        "flight": {
            "number": "248",
            "iataNumber": "ls248",
            "icaoNumber": "exs248"
        }
    },
    {
        "type": "arrival",
        "status": "scheduled",
        "departure": {
            "iataCode": "ibz",
            "icaoCode": "leib",
            "terminal": "1",
            "gate": "10",
            "delay": 185,
            "scheduledTime": "2023-08-20t22:25:00.000",
            "estimatedTime": "2023-08-21t01:30:00.000"
        },
        "arrival": {
            "iataCode": "lba",
            "icaoCode": "egnm",
            "scheduledTime": "2023-08-21t00:20:00.000"
        },
        "airline": {
            "name": "jet2",
            "iataCode": "ls",
            "icaoCode": "exs"
        },
        "flight": {
            "number": "264",
            "iataNumber": "ls264",
            "icaoNumber": "exs264"
        }
    },
    {
        "type": "arrival",
        "status": "landed",
        "departure": {
            "iataCode": "alc",
            "icaoCode": "leal",
            "gate": "130",
            "delay": 8,
            "scheduledTime": "2023-08-20t22:35:00.000",
            "estimatedTime": "2023-08-20t22:35:00.000",
            "actualTime": "2023-08-20t22:42:00.000",
            "estimatedRunway": "2023-08-20t22:42:00.000",
            "actualRunway": "2023-08-20t22:42:00.000"
        },
        "arrival": {
            "iataCode": "lba",
            "icaoCode": "egnm",
            "scheduledTime": "2023-08-21t00:35:00.000",
            "estimatedTime": "2023-08-21t00:10:00.000",
            "actualTime": "2023-08-21t00:04:00.000",
            "estimatedRunway": "2023-08-21t00:04:00.000",
            "actualRunway": "2023-08-21t00:04:00.000"
        },
        "airline": {
            "name": "jet2",
            "iataCode": "ls",
            "icaoCode": "exs"
        },
        "flight": {
            "number": "274",
            "iataNumber": "ls274",
            "icaoNumber": "exs274"
        }
    },
    {
        "type": "arrival",
        "status": "landed",
        "departure": {
            "iataCode": "ace",
            "icaoCode": "gcrr",
            "terminal": "1",
            "gate": "11",
            "delay": 31,
            "scheduledTime": "2023-08-20t20:25:00.000",
            "estimatedTime": "2023-08-20t20:25:00.000",
            "actualTime": "2023-08-20t20:55:00.000",
            "estimatedRunway": "2023-08-20t20:55:00.000",
            "actualRunway": "2023-08-20t20:55:00.000"
        },
        "arrival": {
            "iataCode": "lba",
            "icaoCode": "egnm",
            "scheduledTime": "2023-08-21t00:45:00.000",
            "estimatedTime": "2023-08-21t00:36:00.000",
            "actualTime": "2023-08-21t00:37:00.000",
            "estimatedRunway": "2023-08-21t00:37:00.000",
            "actualRunway": "2023-08-21t00:37:00.000"
        },
        "airline": {
            "name": "jet2",
            "iataCode": "ls",
            "icaoCode": "exs"
        },
        "flight": {
            "number": "218",
            "iataNumber": "ls218",
            "icaoNumber": "exs218"
        }
    },
    {
        "type": "arrival",
        "status": "landed",
        "departure": {
            "iataCode": "pmi",
            "icaoCode": "lepa",
            "gate": "a11",
            "delay": 11,
            "scheduledTime": "2023-08-20t23:10:00.000",
            "estimatedTime": "2023-08-20t23:10:00.000",
            "actualTime": "2023-08-20t23:21:00.000",
            "estimatedRunway": "2023-08-20t23:21:00.000",
            "actualRunway": "2023-08-20t23:21:00.000"
        },
        "arrival": {
            "iataCode": "lba",
            "icaoCode": "egnm",
            "scheduledTime": "2023-08-21t00:55:00.000",
            "estimatedTime": "2023-08-21t00:42:00.000",
            "actualTime": "2023-08-21t00:34:00.000",
            "estimatedRunway": "2023-08-21t00:34:00.000",
            "actualRunway": "2023-08-21t00:34:00.000"
        },
        "airline": {
            "name": "jet2",
            "iataCode": "ls",
            "icaoCode": "exs"
        },
        "flight": {
            "number": "228",
            "iataNumber": "ls228",
            "icaoNumber": "exs228"
        }
    },
    {
        "type": "arrival",
        "status": "landed",
        "departure": {
            "iataCode": "goa",
            "icaoCode": "limj",
            "delay": 26,
            "scheduledTime": "2023-08-20t13:00:00.000",
            "estimatedTime": "2023-08-20t13:10:00.000",
            "actualTime": "2023-08-20t13:26:00.000",
            "estimatedRunway": "2023-08-20t13:26:00.000",
            "actualRunway": "2023-08-20t13:26:00.000"
        },
        "arrival": {
            "iataCode": "lba",
            "icaoCode": "egnm",
            "delay": 15,
            "scheduledTime": "2023-08-20t14:00:00.000",
            "estimatedTime": "2023-08-20t14:15:00.000",
            "actualTime": "2023-08-20t14:15:00.000",
            "estimatedRunway": "2023-08-20t14:15:00.000",
            "actualRunway": "2023-08-20t14:15:00.000"
        },
        "airline": {
            "name": "vistajet",
            "iataCode": "",
            "icaoCode": "vjt"
        },
        "flight": {
            "number": "993",
            "iataNumber": "",
            "icaoNumber": "vjt993"
        }
    }
]