[
    {
        "type": "arrival",
        "status": "landed",
        "departure": {
            "iataCode": "bhd",
            "icaoCode": "egac",
            "delay": 12,
            "scheduledTime": "2024-01-21t07:10:00.000",
            "estimatedTime": "2024-01-21t07:10:00.000",
            "actualTime": "2024-01-21t07:22:00.000",
            "estimatedRunway": "2024-01-21t07:22:00.000",
            "actualRunway": "2024-01-21t07:22:00.000"
        },
        "arrival": {
            "iataCode": "lba",
            "icaoCode": "egnm",
            "scheduledTime": "2024-01-21t08:20:00.000",
            "estimatedTime": "2024-01-21t08:12:00.000",
            "actualTime": "2024-01-21t08:09:00.000",
            "estimatedRunway": "2024-01-21t08:09:00.000",
            "actualRunway": "2024-01-21t08:09:00.000"
        },
        "airline": {
            "name": "british airways",
            "iataCode": "ba",
            "icaoCode": "baw"
        },
        "flight": {
            "number": "8854",
            "iataNumber": "ba8854",
            "icaoNumber": "baw8854"
        },
        "codeshared": {
            "airline": {
                "name": "aer lingus",
                "iataCode": "ei",
                "icaoCode": "ein"
            },
            "flight": {
                "number": "3670",
                "iataNumber": "ei3670",
                "icaoNumber": "ein3670"
            }
        }
    },
    {
        "type": "arrival",
        "status": "landed",
        "departure": {
            "iataCode": "bhd",
            "icaoCode": "egac",
            "delay": 12,
            "scheduledTime": "2024-01-21t07:10:00.000",
            "estimatedTime": "2024-01-21t07:10:00.000",
            "actualTime": "2024-01-21t07:22:00.000",
            "estimatedRunway": "2024-01-21t07:22:00.000",
            "actualRunway": "2024-01-21t07:22:00.000"
        },
        "arrival": {
            "iataCode": "lba",
            "icaoCode": "egnm",
            "scheduledTime": "2024-01-21t08:20:00.000",
            "estimatedTime": "2024-01-21t08:12:00.000",
            "actualTime": "2024-01-21t08:09:00.000",
            "estimatedRunway": "2024-01-21t08:09:00.000",
            "actualRunway": "2024-01-21t08:09:00.000"
        },
        "airline": {
            "name": "aer lingus",
            "iataCode": "ei",
            "icaoCode": "ein"
        },
        "flight": {
            "number": "3670",
            "iataNumber": "ei3670",
            "icaoNumber": "ein3670"
        }
    },
    {
        "type": "arrival",
        "status": "landed",
        "departure": {
            "iataCode": "dub",
            "icaoCode": "eidw",
            "terminal": "2",
            "gate": "334",
            "delay": 11,
            "scheduledTime": "2024-01-21t07:10:00.000",
            "estimatedTime": "2024-01-21t07:38:00.000",
            "actualTime": "2024-01-21t07:21:00.000",
            "estimatedRunway": "2024-01-21t07:21:00.000",
            "actualRunway": "2024-01-21t07:21:00.000"
        },
        "arrival": {
            "iataCode": "lba",
            "icaoCode": "egnm",
            "scheduledTime": "2024-01-21t08:25:00.000",
            "estimatedTime": "2024-01-21t08:10:00.000",
            "actualTime": "2024-01-21t08:03:00.000",
            "estimatedRunway": "2024-01-21t08:03:00.000",
            "actualRunway": "2024-01-21t08:03:00.000"
        },
        "airline": {
            "name": "british airways",
            "iataCode": "ba",
            "icaoCode": "baw"
        },
        "flight": {
            "number": "8960",
            "iataNumber": "ba8960",
            "icaoNumber": "baw8960"
        },
        "codeshared": {
            "airline": {
                "name": "aer lingus",
                "iataCode": "ei",
                "icaoCode": "ein"
            },
            "flight": {
                "number": "3390",
                "iataNumber": "ei3390",
                "icaoNumber": "ein3390"
            }
        }
    },
    {
        "type": "arrival",
        "status": "landed",
        "departure": {
            "iataCode": "dub",
            "icaoCode": "eidw",
            "terminal": "2",
            "gate": "334",
            "delay": 11,
            "scheduledTime": "2024-01-21t07:10:00.000",
            "estimatedTime": "2024-01-21t07:38:00.000",
            "actualTime": "2024-01-21t07:21:00.000",
            "estimatedRunway": "2024-01-21t07:21:00.000",
            "actualRunway": "2024-01-21t07:21:00.000"
        },
        "arrival": {
            "iataCode": "lba",
            "icaoCode": "egnm",
            "scheduledTime": "2024-01-21t08:25:00.000",
            "estimatedTime": "2024-01-21t08:10:00.000",
            "actualTime": "2024-01-21t08:03:00.000",
            "estimatedRunway": "2024-01-21t08:03:00.000",
            "actualRunway": "2024-01-21t08:03:00.000"
        },
        "airline": {
            "name": "aer lingus",
            "iataCode": "ei",
            "icaoCode": "ein"
        },
        "flight": {
            "number": "3390",
            "iataNumber": "ei3390",
            "icaoNumber": "ein3390"
        }
    },
    {
        "type": "arrival",
        "status": "landed",
        "departure": {
            "iataCode": "dub",
            "icaoCode": "eidw",
            "terminal": "1",
            "gate": "112",
            "delay": 6,
            "scheduledTime": "2024-01-21t07:25:00.000",
            "estimatedTime": "2024-01-21t07:25:00.000",
            "actualTime": "2024-01-21t07:31:00.000",
            "estimatedRunway": "2024-01-21t07:31:00.000",
            "actualRunway": "2024-01-21t07:31:00.000"
        },
        "arrival": {
            "iataCode": "lba",
            "icaoCode": "egnm",
            "gate": "112",
            "scheduledTime": "2024-01-21t08:25:00.000",
            "actualTime": "2024-01-21t08:06:00.000",
            "estimatedRunway": "2024-01-21t08:06:00.000",
            "actualRunway": "2024-01-21t08:06:00.000"
        },
        "airline": {
            "name": "ryanair",
            "iataCode": "fr",
            "icaoCode": "ryr"
        },
        "flight": {
            "number": "152",
            "iataNumber": "fr152",
            "icaoNumber": "ryr152"
        }
    },
    {
        "type": "arrival",
        "status": "landed",
        "departure": {
            "iataCode": "ams",
            "icaoCode": "eham",
            "terminal": "2",
            "gate": "d6",
            "delay": 12,
            "scheduledTime": "2024-01-21t09:25:00.000",
            "estimatedTime": "2024-01-21t09:33:00.000",
            "actualTime": "2024-01-21t09:36:00.000",
            "estimatedRunway": "2024-01-21t09:36:00.000",
            "actualRunway": "2024-01-21t09:36:00.000"
        },
        "arrival": {
            "iataCode": "lba",
            "icaoCode": "egnm",
            "scheduledTime": "2024-01-21t09:30:00.000",
            "estimatedTime": "2024-01-21t09:38:00.000",
            "actualTime": "2024-01-21t09:28:00.000",
            "estimatedRunway": "2024-01-21t09:28:00.000",
            "actualRunway": "2024-01-21t09:28:00.000"
        },
        "airline": {
            "name": "delta air lines",
            "iataCode": "dl",
            "icaoCode": "dal"
        },
        "flight": {
            "number": "9638",
            "iataNumber": "dl9638",
            "icaoNumber": "dal9638"
        },
        "codeshared": {
            "airline": {
                "name": "klm",
                "iataCode": "kl",
                "icaoCode": "klm"
            },
            "flight": {
                "number": "1545",
                "iataNumber": "kl1545",
                "icaoNumber": "klm1545"
            }
        }
    },
    {
        "type": "arrival",
        "status": "landed",
        "departure": {
            "iataCode": "ams",
            "icaoCode": "eham",
            "terminal": "2",
            "gate": "d6",
            "delay": 12,
            "scheduledTime": "2024-01-21t09:25:00.000",
            "estimatedTime": "2024-01-21t09:33:00.000",
            "actualTime": "2024-01-21t09:36:00.000",
            "estimatedRunway": "2024-01-21t09:36:00.000",
            "actualRunway": "2024-01-21t09:36:00.000"
        },
        "arrival": {
            "iataCode": "lba",
            "icaoCode": "egnm",
            "scheduledTime": "2024-01-21t09:30:00.000",
            "estimatedTime": "2024-01-21t09:38:00.000",
            "actualTime": "2024-01-21t09:28:00.000",
            "estimatedRunway": "2024-01-21t09:28:00.000",
            "actualRunway": "2024-01-21t09:28:00.000"
        },
        "airline": {
            "name": "kenya airways",
            "iataCode": "kq",
            "icaoCode": "kqa"
        },
        "flight": {
            "number": "1545",
            "iataNumber": "kq1545",
            "icaoNumber": "kqa1545"
        },
        "codeshared": {
            "airline": {
                "name": "klm",
                "iataCode": "kl",
                "icaoCode": "klm"
            },
            "flight": {
                "number": "1545",
                "iataNumber": "kl1545",
                "icaoNumber": "klm1545"
            }
        }
    },
    {
        "type": "arrival",
        "status": "landed",
        "departure": {
            "iataCode": "ams",
            "icaoCode": "eham",
            "terminal": "2",
            "gate": "d6",
            "delay": 12,
            "scheduledTime": "2024-01-21t09:25:00.000",
            "estimatedTime": "2024-01-21t09:33:00.000",
            "actualTime": "2024-01-21t09:36:00.000",
            "estimatedRunway": "2024-01-21t09:36:00.000",
            "actualRunway": "2024-01-21t09:36:00.000"
        },
        "arrival": {
            "iataCode": "lba",
            "icaoCode": "egnm",
            "scheduledTime": "2024-01-21t09:30:00.000",
            "estimatedTime": "2024-01-21t09:38:00.000",
            "actualTime": "2024-01-21t09:28:00.000",
            "estimatedRunway": "2024-01-21t09:28:00.000",
            "actualRunway": "2024-01-21t09:28:00.000"
        },
        "airline": {
            "name": "china eastern airlines",
            "iataCode": "mu",
            "icaoCode": "ces"
        },
        "flight": {
            "number": "1633",
            "iataNumber": "mu1633",
            "icaoNumber": "ces1633"
        },
        "codeshared": {
            "airline": {
                "name": "klm",
                "iataCode": "kl",
                "icaoCode": "klm"
            },
            "flight": {
                "number": "1545",
                "iataNumber": "kl1545",
                "icaoNumber": "klm1545"
            }
        }
    },
    {
        "type": "arrival",
        "status": "landed",
        "departure": {
            "iataCode": "ams",
            "icaoCode": "eham",
            "terminal": "2",
            "gate": "d6",
            "delay": 12,
            "scheduledTime": "2024-01-21t09:25:00.000",
            "estimatedTime": "2024-01-21t09:33:00.000",
            "actualTime": "2024-01-21t09:36:00.000",
            "estimatedRunway": "2024-01-21t09:36:00.000",
            "actualRunway": "2024-01-21t09:36:00.000"
        },
        "arrival": {
            "iataCode": "lba",
            "icaoCode": "egnm",
            "scheduledTime": "2024-01-21t09:30:00.000",
            "estimatedTime": "2024-01-21t09:38:00.000",
            "actualTime": "2024-01-21t09:28:00.000",
            "estimatedRunway": "2024-01-21t09:28:00.000",
            "actualRunway": "2024-01-21t09:28:00.000"
        },
        "airline": {
            "name": "virgin atlantic",
            "iataCode": "vs",
            "icaoCode": "vir"
        },
        "flight": {
            "number": "6981",
            "iataNumber": "vs6981",
            "icaoNumber": "vir6981"
        },
        "codeshared": {
            "airline": {
                "name": "klm",
                "iataCode": "kl",
                "icaoCode": "klm"
            },
            "flight": {
                "number": "1545",
                "iataNumber": "kl1545",
                "icaoNumber": "klm1545"
            }
        }
    },
    {
        "type": "arrival",
        "status": "landed",
        "departure": {
            "iataCode": "ams",
            "icaoCode": "eham",
            "terminal": "2",
            "gate": "d6",
            "delay": 12,
            "scheduledTime": "2024-01-21t09:25:00.000",
            "estimatedTime": "2024-01-21t09:33:00.000",
            "actualTime": "2024-01-21t09:36:00.000",
            "estimatedRunway": "2024-01-21t09:36:00.000",
            "actualRunway": "2024-01-21t09:36:00.000"
        },
        "arrival": {
            "iataCode": "lba",
            "icaoCode": "egnm",
            "scheduledTime": "2024-01-21t09:30:00.000",
            "estimatedTime": "2024-01-21t09:38:00.000",
            "actualTime": "2024-01-21t09:28:00.000",
            "estimatedRunway": "2024-01-21t09:28:00.000",
            "actualRunway": "2024-01-21t09:28:00.000"
        },
        "airline": {
            "name": "klm",
            "iataCode": "kl",
            "icaoCode": "klm"
        },
        "flight": {
            "number": "1545",
            "iataNumber": "kl1545",
            "icaoNumber": "klm1545"
        }
    },
    {
        "type": "arrival",
        "status": "landed",
        "departure": {
            "iataCode": "opo",
            "icaoCode": "lppr",
            "delay": 6,
            "scheduledTime": "2024-01-21t09:05:00.000",
            "estimatedTime": "2024-01-21t09:05:00.000",
            "actualTime": "2024-01-21t09:11:00.000",
            "estimatedRunway": "2024-01-21t09:11:00.000",
            "actualRunway": "2024-01-21t09:11:00.000"
        },
        "arrival": {
            "iataCode": "lba",
            "icaoCode": "egnm",
            "gate": "12",
            "scheduledTime": "2024-01-21t11:40:00.000",
            "estimatedTime": "2024-01-21t11:24:00.000",
            "actualTime": "2024-01-21t11:26:00.000",
            "estimatedRunway": "2024-01-21t11:26:00.000",
            "actualRunway": "2024-01-21t11:26:00.000"
        },
        "airline": {
            "name": "ryanair",
            "iataCode": "fr",
            "icaoCode": "ryr"
        },
        "flight": {
            "number": "2400",
            "iataNumber": "fr2400",
            "icaoNumber": "ryr2400"
        }
    },
    {
        "type": "arrival",
        "status": "diverted",
        "departure": {
            "iataCode": "gdn",
            "icaoCode": "epgd",
            "delay": 6,
            "scheduledTime": "2024-01-21t11:05:00.000",
            "estimatedTime": "2024-01-21t11:05:00.000",
            "actualTime": "2024-01-21t11:10:00.000",
            "estimatedRunway": "2024-01-21t11:10:00.000",
            "actualRunway": "2024-01-21t11:10:00.000"
        },
        "arrival": {
            "iataCode": "lba",
            "icaoCode": "egnm",
            "gate": "27",
            "delay": 4,
            "scheduledTime": "2024-01-21t12:30:00.000",
            "estimatedTime": "2024-01-21t12:33:00.000"
        },
        "airline": {
            "name": "ryanair",
            "iataCode": "fr",
            "icaoCode": "ryr"
        },
        "flight": {
            "number": "1504",
            "iataNumber": "fr1504",
            "icaoNumber": "ryr1504"
        }
    },
    {
        "type": "arrival",
        "status": "diverted",
        "departure": {
            "iataCode": "ams",
            "icaoCode": "eham",
            "terminal": "2",
            "gate": "d6",
            "delay": 17,
            "scheduledTime": "2024-01-21t13:15:00.000",
            "estimatedTime": "2024-01-21t13:30:00.000",
            "actualTime": "2024-01-21t13:32:00.000",
            "estimatedRunway": "2024-01-21t13:32:00.000",
            "actualRunway": "2024-01-21t13:32:00.000"
        },
        "arrival": {
            "iataCode": "lba",
            "icaoCode": "egnm",
            "delay": 3,
            "scheduledTime": "2024-01-21t13:25:00.000",
            "estimatedTime": "2024-01-21t13:27:00.000"
        },
        "airline": {
            "name": "delta air lines",
            "iataCode": "dl",
            "icaoCode": "dal"
        },
        "flight": {
            "number": "9464",
            "iataNumber": "dl9464",
            "icaoNumber": "dal9464"
        },
        "codeshared": {
            "airline": {
                "name": "klm",
                "iataCode": "kl",
                "icaoCode": "klm"
            },
            "flight": {
                "number": "1547",
                "iataNumber": "kl1547",
                "icaoNumber": "klm1547"
            }
        }
    },
    {
        "type": "arrival",
        "status": "diverted",
        "departure": {
            "iataCode": "ams",
            "icaoCode": "eham",
            "terminal": "2",
            "gate": "d6",
            "delay": 17,
            "scheduledTime": "2024-01-21t13:15:00.000",
            "estimatedTime": "2024-01-21t13:30:00.000",
            "actualTime": "2024-01-21t13:32:00.000",
            "estimatedRunway": "2024-01-21t13:32:00.000",
            "actualRunway": "2024-01-21t13:32:00.000"
        },
        "arrival": {
            "iataCode": "lba",
            "icaoCode": "egnm",
            "delay": 3,
            "scheduledTime": "2024-01-21t13:25:00.000",
            "estimatedTime": "2024-01-21t13:27:00.000"
        },
        "airline": {
            "name": "virgin atlantic",
            "iataCode": "vs",
            "icaoCode": "vir"
        },
        "flight": {
            "number": "7107",
            "iataNumber": "vs7107",
            "icaoNumber": "vir7107"
        },
        "codeshared": {
            "airline": {
                "name": "klm",
                "iataCode": "kl",
                "icaoCode": "klm"
            },
            "flight": {
                "number": "1547",
                "iataNumber": "kl1547",
                "icaoNumber": "klm1547"
            }
        }
    },
    {
        "type": "arrival",
        "status": "diverted",
        "departure": {
            "iataCode": "ams",
            "icaoCode": "eham",
            "terminal": "2",
            "gate": "d6",
            "delay": 17,
            "scheduledTime": "2024-01-21t13:15:00.000",
            "estimatedTime": "2024-01-21t13:30:00.000",
            "actualTime": "2024-01-21t13:32:00.000",
            "estimatedRunway": "2024-01-21t13:32:00.000",
            "actualRunway": "2024-01-21t13:32:00.000"
        },
        "arrival": {
            "iataCode": "lba",
            "icaoCode": "egnm",
            "delay": 3,
            "scheduledTime": "2024-01-21t13:25:00.000",
            "estimatedTime": "2024-01-21t13:27:00.000"
        },
        "airline": {
            "name": "klm",
            "iataCode": "kl",
            "icaoCode": "klm"
        },
        "flight": {
            "number": "1547",
            "iataNumber": "kl1547",
            "icaoNumber": "klm1547"
        }
    },
    {
        "type": "arrival",
        "status": "landed",
        "departure": {
            "iataCode": "alc",
            "icaoCode": "leal",
            "gate": "136",
            "delay": 7,
            "scheduledTime": "2024-01-21t11:40:00.000",
            "estimatedTime": "2024-01-21t11:40:00.000",
            "actualTime": "2024-01-21t11:46:00.000",
            "estimatedRunway": "2024-01-21t11:46:00.000",
            "actualRunway": "2024-01-21t11:46:00.000"
        },
        "arrival": {
            "iataCode": "lba",
            "icaoCode": "egnm",
            "delay": 26,
            "scheduledTime": "2024-01-21t13:40:00.000",
            "estimatedTime": "2024-01-21t13:31:00.000",
            "actualTime": "2024-01-21t14:06:00.000",
            "estimatedRunway": "2024-01-21t14:06:00.000",
            "actualRunway": "2024-01-21t14:06:00.000"
        },
        "airline": {
            "name": "jet2",
            "iataCode": "ls",
            "icaoCode": "exs"
        },
        "flight": {
            "number": "272",
            "iataNumber": "ls272",
            "icaoNumber": "exs272"
        }
    },
    {
        "type": "arrival",
        "status": "cancelled",
        "departure": {
            "iataCode": "dub",
            "icaoCode": "eidw",
            "terminal": "2",
            "gate": "334",
            "scheduledTime": "2024-01-21t13:30:00.000",
            "estimatedTime": "2024-01-21t13:30:00.000"
        },
        "arrival": {
            "iataCode": "lba",
            "icaoCode": "egnm",
            "scheduledTime": "2024-01-21t14:45:00.000"
        },
        "airline": {
            "name": "british airways",
            "iataCode": "ba",
            "icaoCode": "baw"
        },
        "flight": {
            "number": "8870",
            "iataNumber": "ba8870",
            "icaoNumber": "baw8870"
        },
        "codeshared": {
            "airline": {
                "name": "aer lingus",
                "iataCode": "ei",
                "icaoCode": "ein"
            },
            "flight": {
                "number": "3392",
                "iataNumber": "ei3392",
                "icaoNumber": "ein3392"
            }
        }
    },
    {
        "type": "arrival",
        "status": "cancelled",
        "departure": {
            "iataCode": "dub",
            "icaoCode": "eidw",
            "terminal": "2",
            "gate": "334",
            "scheduledTime": "2024-01-21t13:30:00.000",
            "estimatedTime": "2024-01-21t13:30:00.000"
        },
        "arrival": {
            "iataCode": "lba",
            "icaoCode": "egnm",
            "scheduledTime": "2024-01-21t14:45:00.000"
        },
        "airline": {
            "name": "aer lingus",
            "iataCode": "ei",
            "icaoCode": "ein"
        },
        "flight": {
            "number": "3392",
            "iataNumber": "ei3392",
            "icaoNumber": "ein3392"
        }
    },
    {
        "type": "arrival",
        "status": "scheduled",
        "departure": {
            "iataCode": "dub",
            "icaoCode": "eidw",
            "terminal": "1",
            "gate": "102",
            "scheduledTime": "2024-01-21t14:10:00.000",
            "estimatedTime": "2024-01-21t14:10:00.000"
        },
        "arrival": {
            "iataCode": "lba",
            "icaoCode": "egnm",
            "gate": "102",
            "scheduledTime": "2024-01-21t15:10:00.000"
        },
        "airline": {
            "name": "ryanair",
            "iataCode": "fr",
            "icaoCode": "ryr"
        },
        "flight": {
            "number": "156",
            "iataNumber": "fr156",
            "icaoNumber": "ryr156"
        }
    },
    {
        "type": "arrival",
        "status": "landed",
        "departure": {
            "iataCode": "agp",
            "icaoCode": "lemg",
            "gate": "363",
            "delay": 8,
            "scheduledTime": "2024-01-21t13:25:00.000",
            "estimatedTime": "2024-01-21t13:25:00.000",
            "actualTime": "2024-01-21t13:32:00.000",
            "estimatedRunway": "2024-01-21t13:32:00.000",
            "actualRunway": "2024-01-21t13:32:00.000"
        },
        "arrival": {
            "iataCode": "lba",
            "icaoCode": "egnm",
            "gate": "c30",
            "scheduledTime": "2024-01-21t15:30:00.000",
            "estimatedTime": "2024-01-21t15:27:00.000",
            "actualTime": "2024-01-21t15:30:00.000",
            "estimatedRunway": "2024-01-21t15:30:00.000",
            "actualRunway": "2024-01-21t15:30:00.000"
        },
        "airline": {
            "name": "ryanair",
            "iataCode": "fr",
            "icaoCode": "ryr"
        },
        "flight": {
            "number": "2447",
            "iataNumber": "fr2447",
            "icaoNumber": "ryr2447"
        }
    },
    {
        "type": "arrival",
        "status": "landed",
        "departure": {
            "iataCode": "gva",
            "icaoCode": "lsgg",
            "terminal": "2",
            "gate": "d82",
            "delay": 23,
            "scheduledTime": "2024-01-21t15:10:00.000",
            "estimatedTime": "2024-01-21t15:10:00.000",
            "actualTime": "2024-01-21t15:32:00.000",
            "estimatedRunway": "2024-01-21t15:32:00.000",
            "actualRunway": "2024-01-21t15:32:00.000"
        },
        "arrival": {
            "iataCode": "lba",
            "icaoCode": "egnm",
            "delay": 9,
            "scheduledTime": "2024-01-21t16:10:00.000",
            "estimatedTime": "2024-01-21t16:17:00.000",
            "actualTime": "2024-01-21t16:18:00.000",
            "estimatedRunway": "2024-01-21t16:18:00.000",
            "actualRunway": "2024-01-21t16:18:00.000"
        },
        "airline": {
            "name": "jet2",
            "iataCode": "ls",
            "icaoCode": "exs"
        },
        "flight": {
            "number": "286",
            "iataNumber": "ls286",
            "icaoNumber": "exs286"
        }
    },
    {
        "type": "arrival",
        "status": "landed",
        "departure": {
            "iataCode": "fnc",
            "icaoCode": "lpma",
            "terminal": "t1",
            "delay": 1,
            "scheduledTime": "2024-01-21t12:10:00.000",
            "estimatedTime": "2024-01-21t12:18:00.000",
            "actualTime": "2024-01-21t12:10:00.000",
            "estimatedRunway": "2024-01-21t12:10:00.000",
            "actualRunway": "2024-01-21t12:10:00.000"
        },
        "arrival": {
            "iataCode": "lba",
            "icaoCode": "egnm",
            "scheduledTime": "2024-01-21t16:10:00.000",
            "estimatedTime": "2024-01-21t15:40:00.000",
            "actualTime": "2024-01-21t15:43:00.000",
            "estimatedRunway": "2024-01-21t15:43:00.000",
            "actualRunway": "2024-01-21t15:43:00.000"
        },
        "airline": {
            "name": "jet2",
            "iataCode": "ls",
            "icaoCode": "exs"
        },
        "flight": {
            "number": "390",
            "iataNumber": "ls390",
            "icaoNumber": "exs390"
        }
    },
    {
        "type": "arrival",
        "status": "scheduled",
        "departure": {
            "iataCode": "ams",
            "icaoCode": "eham",
            "terminal": "2",
            "gate": "d6",
            "delay": 18,
            "scheduledTime": "2024-01-21t16:35:00.000",
            "estimatedTime": "2024-01-21t16:44:00.000",
            "actualTime": "2024-01-21t16:53:00.000",
            "estimatedRunway": "2024-01-21t16:53:00.000",
            "actualRunway": "2024-01-21t16:53:00.000"
        },
        "arrival": {
            "iataCode": "lba",
            "icaoCode": "egnm",
            "delay": 21,
            "scheduledTime": "2024-01-21t16:45:00.000",
            "estimatedTime": "2024-01-21t17:05:00.000"
        },
        "airline": {
            "name": "air france",
            "iataCode": "af",
            "icaoCode": "afr"
        },
        "flight": {
            "number": "8387",
            "iataNumber": "af8387",
            "icaoNumber": "afr8387"
        },
        "codeshared": {
            "airline": {
                "name": "german airways",
                "iataCode": "zq",
                "icaoCode": "ger"
            },
            "flight": {
                "number": "1549",
                "iataNumber": "zq1549",
                "icaoNumber": "ger1549"
            }
        }
    },
    {
        "type": "arrival",
        "status": "scheduled",
        "departure": {
            "iataCode": "ams",
            "icaoCode": "eham",
            "terminal": "2",
            "gate": "d6",
            "delay": 18,
            "scheduledTime": "2024-01-21t16:35:00.000",
            "estimatedTime": "2024-01-21t16:44:00.000",
            "actualTime": "2024-01-21t16:53:00.000",
            "estimatedRunway": "2024-01-21t16:53:00.000",
            "actualRunway": "2024-01-21t16:53:00.000"
        },
        "arrival": {
            "iataCode": "lba",
            "icaoCode": "egnm",
            "delay": 21,
            "scheduledTime": "2024-01-21t16:45:00.000",
            "estimatedTime": "2024-01-21t17:05:00.000"
        },
        "airline": {
            "name": "delta air lines",
            "iataCode": "dl",
            "icaoCode": "dal"
        },
        "flight": {
            "number": "9251",
            "iataNumber": "dl9251",
            "icaoNumber": "dal9251"
        },
        "codeshared": {
            "airline": {
                "name": "german airways",
                "iataCode": "zq",
                "icaoCode": "ger"
            },
            "flight": {
                "number": "1549",
                "iataNumber": "zq1549",
                "icaoNumber": "ger1549"
            }
        }
    },
    {
        "type": "arrival",
        "status": "scheduled",
        "departure": {
            "iataCode": "ams",
            "icaoCode": "eham",
            "terminal": "2",
            "gate": "d6",
            "delay": 18,
            "scheduledTime": "2024-01-21t16:35:00.000",
            "estimatedTime": "2024-01-21t16:44:00.000",
            "actualTime": "2024-01-21t16:53:00.000",
            "estimatedRunway": "2024-01-21t16:53:00.000",
            "actualRunway": "2024-01-21t16:53:00.000"
        },
        "arrival": {
            "iataCode": "lba",
            "icaoCode": "egnm",
            "delay": 21,
            "scheduledTime": "2024-01-21t16:45:00.000",
            "estimatedTime": "2024-01-21t17:05:00.000"
        },
        "airline": {
            "name": "gol",
            "iataCode": "g3",
            "icaoCode": "glo"
        },
        "flight": {
            "number": "5552",
            "iataNumber": "g35552",
            "icaoNumber": "glo5552"
        },
        "codeshared": {
            "airline": {
                "name": "german airways",
                "iataCode": "zq",
                "icaoCode": "ger"
            },
            "flight": {
                "number": "1549",
                "iataNumber": "zq1549",
                "icaoNumber": "ger1549"
            }
        }
    },
    {
        "type": "arrival",
        "status": "scheduled",
        "departure": {
            "iataCode": "ams",
            "icaoCode": "eham",
            "terminal": "2",
            "gate": "d6",
            "delay": 18,
            "scheduledTime": "2024-01-21t16:35:00.000",
            "estimatedTime": "2024-01-21t16:44:00.000",
            "actualTime": "2024-01-21t16:53:00.000",
            "estimatedRunway": "2024-01-21t16:53:00.000",
            "actualRunway": "2024-01-21t16:53:00.000"
        },
        "arrival": {
            "iataCode": "lba",
            "icaoCode": "egnm",
            "delay": 21,
            "scheduledTime": "2024-01-21t16:45:00.000",
            "estimatedTime": "2024-01-21t17:05:00.000"
        },
        "airline": {
            "name": "kenya airways",
            "iataCode": "kq",
            "icaoCode": "kqa"
        },
        "flight": {
            "number": "1549",
            "iataNumber": "kq1549",
            "icaoNumber": "kqa1549"
        },
        "codeshared": {
            "airline": {
                "name": "german airways",
                "iataCode": "zq",
                "icaoCode": "ger"
            },
            "flight": {
                "number": "1549",
                "iataNumber": "zq1549",
                "icaoNumber": "ger1549"
            }
        }
    },
    {
        "type": "arrival",
        "status": "scheduled",
        "departure": {
            "iataCode": "ams",
            "icaoCode": "eham",
            "terminal": "2",
            "gate": "d6",
            "delay": 18,
            "scheduledTime": "2024-01-21t16:35:00.000",
            "estimatedTime": "2024-01-21t16:44:00.000",
            "actualTime": "2024-01-21t16:53:00.000",
            "estimatedRunway": "2024-01-21t16:53:00.000",
            "actualRunway": "2024-01-21t16:53:00.000"
        },
        "arrival": {
            "iataCode": "lba",
            "icaoCode": "egnm",
            "delay": 21,
            "scheduledTime": "2024-01-21t16:45:00.000",
            "estimatedTime": "2024-01-21t17:05:00.000"
        },
        "airline": {
            "name": "virgin atlantic",
            "iataCode": "vs",
            "icaoCode": "vir"
        },
        "flight": {
            "number": "6982",
            "iataNumber": "vs6982",
            "icaoNumber": "vir6982"
        },
        "codeshared": {
            "airline": {
                "name": "german airways",
                "iataCode": "zq",
                "icaoCode": "ger"
            },
            "flight": {
                "number": "1549",
                "iataNumber": "zq1549",
                "icaoNumber": "ger1549"
            }
        }
    },
    {
        "type": "arrival",
        "status": "scheduled",
        "departure": {
            "iataCode": "ams",
            "icaoCode": "eham",
            "terminal": "2",
            "gate": "d6",
            "delay": 18,
            "scheduledTime": "2024-01-21t16:35:00.000",
            "estimatedTime": "2024-01-21t16:44:00.000",
            "actualTime": "2024-01-21t16:53:00.000",
            "estimatedRunway": "2024-01-21t16:53:00.000",
            "actualRunway": "2024-01-21t16:53:00.000"
        },
        "arrival": {
            "iataCode": "lba",
            "icaoCode": "egnm",
            "delay": 21,
            "scheduledTime": "2024-01-21t16:45:00.000",
            "estimatedTime": "2024-01-21t17:05:00.000"
        },
        "airline": {
            "name": "german airways",
            "iataCode": "zq",
            "icaoCode": "ger"
        },
        "flight": {
            "number": "1549",
            "iataNumber": "zq1549",
            "icaoNumber": "ger1549"
        }
    },
    {
        "type": "arrival",
        "status": "landed",
        "departure": {
            "iataCode": "fao",
            "icaoCode": "lpfr",
            "delay": 2,
            "scheduledTime": "2024-01-21t13:45:00.000",
            "estimatedTime": "2024-01-21t13:55:00.000",
            "actualTime": "2024-01-21t13:47:00.000",
            "estimatedRunway": "2024-01-21t13:47:00.000",
            "actualRunway": "2024-01-21t13:47:00.000"
        },
        "arrival": {
            "iataCode": "lba",
            "icaoCode": "egnm",
            "scheduledTime": "2024-01-21t16:55:00.000",
            "estimatedTime": "2024-01-21t16:38:00.000",
            "actualTime": "2024-01-21t16:42:00.000",
            "estimatedRunway": "2024-01-21t16:42:00.000",
            "actualRunway": "2024-01-21t16:42:00.000"
        },
        "airline": {
            "name": "jet2",
            "iataCode": "ls",
            "icaoCode": "exs"
        },
        "flight": {
            "number": "252",
            "iataNumber": "ls252",
            "icaoNumber": "exs252"
        }
    },
    {
        "type": "arrival",
        "status": "active",
        "departure": {
            "iataCode": "ayt",
            "icaoCode": "ltai",
            "terminal": "1",
            "gate": "146",
            "delay": 7,
            "scheduledTime": "2024-01-21t16:15:00.000",
            "estimatedTime": "2024-01-21t16:15:00.000",
            "actualTime": "2024-01-21t16:21:00.000",
            "estimatedRunway": "2024-01-21t16:21:00.000",
            "actualRunway": "2024-01-21t16:21:00.000"
        },
        "arrival": {
            "iataCode": "lba",
            "icaoCode": "egnm",
            "delay": 9,
            "scheduledTime": "2024-01-21t18:05:00.000",
            "estimatedTime": "2024-01-21t18:14:00.000"
        },
        "airline": {
            "name": "jet2",
            "iataCode": "ls",
            "icaoCode": "exs"
        },
        "flight": {
            "number": "214",
            "iataNumber": "ls214",
            "icaoNumber": "exs214"
        }
    },
    {
        "type": "arrival",
        "status": "landed",
        "departure": {
            "iataCode": "tfs",
            "icaoCode": "gcts",
            "gate": "62",
            "delay": 10,
            "scheduledTime": "2024-01-21t13:40:00.000",
            "estimatedTime": "2024-01-21t13:40:00.000",
            "actualTime": "2024-01-21t13:49:00.000",
            "estimatedRunway": "2024-01-21t13:49:00.000",
            "actualRunway": "2024-01-21t13:49:00.000"
        },
        "arrival": {
            "iataCode": "lba",
            "icaoCode": "egnm",
            "scheduledTime": "2024-01-21t18:25:00.000",
            "estimatedTime": "2024-01-21t17:53:00.000",
            "actualTime": "2024-01-21t17:54:00.000",
            "estimatedRunway": "2024-01-21t17:54:00.000",
            "actualRunway": "2024-01-21t17:54:00.000"
        },
        "airline": {
            "name": "jet2",
            "iataCode": "ls",
            "icaoCode": "exs"
        },
        "flight": {
            "number": "224",
            "iataNumber": "ls224",
            "icaoNumber": "exs224"
        }
    },
    {
        "type": "arrival",
        "status": "cancelled",
        "departure": {
            "iataCode": "bhd",
            "icaoCode": "egac",
            "scheduledTime": "2024-01-21t17:35:00.000",
            "estimatedTime": "2024-01-21t17:35:00.000"
        },
        "arrival": {
            "iataCode": "lba",
            "icaoCode": "egnm",
            "scheduledTime": "2024-01-21t18:45:00.000"
        },
        "airline": {
            "name": "british airways",
            "iataCode": "ba",
            "icaoCode": "baw"
        },
        "flight": {
            "number": "8986",
            "iataNumber": "ba8986",
            "icaoNumber": "baw8986"
        },
        "codeshared": {
            "airline": {
                "name": "aer lingus",
                "iataCode": "ei",
                "icaoCode": "ein"
            },
            "flight": {
                "number": "3678",
                "iataNumber": "ei3678",
                "icaoNumber": "ein3678"
            }
        }
    },
    {
        "type": "arrival",
        "status": "cancelled",
        "departure": {
            "iataCode": "bhd",
            "icaoCode": "egac",
            "scheduledTime": "2024-01-21t17:35:00.000",
            "estimatedTime": "2024-01-21t17:35:00.000"
        },
        "arrival": {
            "iataCode": "lba",
            "icaoCode": "egnm",
            "scheduledTime": "2024-01-21t18:45:00.000"
        },
        "airline": {
            "name": "aer lingus",
            "iataCode": "ei",
            "icaoCode": "ein"
        },
        "flight": {
            "number": "3678",
            "iataNumber": "ei3678",
            "icaoNumber": "ein3678"
        }
    },
    {
        "type": "arrival",
        "status": "landed",
        "departure": {
            "iataCode": "ace",
            "icaoCode": "gcrr",
            "terminal": "1",
            "gate": "9",
            "delay": 12,
            "scheduledTime": "2024-01-21t15:10:00.000",
            "estimatedTime": "2024-01-21t15:08:00.000",
            "actualTime": "2024-01-21t15:21:00.000",
            "estimatedRunway": "2024-01-21t15:21:00.000",
            "actualRunway": "2024-01-21t15:21:00.000"
        },
        "arrival": {
            "iataCode": "lba",
            "icaoCode": "egnm",
            "scheduledTime": "2024-01-21t19:40:00.000",
            "estimatedTime": "2024-01-21t19:18:00.000",
            "actualTime": "2024-01-21t19:16:00.000",
            "estimatedRunway": "2024-01-21t19:16:00.000",
            "actualRunway": "2024-01-21t19:16:00.000"
        },
        "airline": {
            "name": "jet2",
            "iataCode": "ls",
            "icaoCode": "exs"
        },
        "flight": {
            "number": "218",
            "iataNumber": "ls218",
            "icaoNumber": "exs218"
        }
    },
    {
        "type": "arrival",
        "status": "landed",
        "departure": {
            "iataCode": "prg",
            "icaoCode": "lkpr",
            "terminal": "1",
            "gate": "b8",
            "delay": 7,
            "scheduledTime": "2024-01-21t18:30:00.000",
            "estimatedTime": "2024-01-21t18:39:00.000",
            "actualTime": "2024-01-21t18:37:00.000",
            "estimatedRunway": "2024-01-21t18:37:00.000",
            "actualRunway": "2024-01-21t18:37:00.000"
        },
        "arrival": {
            "iataCode": "lba",
            "icaoCode": "egnm",
            "baggage": "41",
            "scheduledTime": "2024-01-21t19:45:00.000",
            "estimatedTime": "2024-01-21t19:33:00.000",
            "actualTime": "2024-01-21t19:32:00.000",
            "estimatedRunway": "2024-01-21t19:32:00.000",
            "actualRunway": "2024-01-21t19:32:00.000"
        },
        "airline": {
            "name": "jet2",
            "iataCode": "ls",
            "icaoCode": "exs"
        },
        "flight": {
            "number": "204",
            "iataNumber": "ls204",
            "icaoNumber": "exs204"
        }
    },
    {
        "type": "arrival",
        "status": "active",
        "departure": {
            "iataCode": "lpa",
            "icaoCode": "gclp",
            "gate": "216",
            "delay": 30,
            "scheduledTime": "2024-01-21t15:15:00.000",
            "estimatedTime": "2024-01-21t15:15:00.000",
            "actualTime": "2024-01-21t15:45:00.000",
            "estimatedRunway": "2024-01-21t15:45:00.000",
            "actualRunway": "2024-01-21t15:45:00.000"
        },
        "arrival": {
            "iataCode": "lba",
            "icaoCode": "egnm",
            "scheduledTime": "2024-01-21t19:55:00.000",
            "estimatedTime": "2024-01-21t19:53:00.000"
        },
        "airline": {
            "name": "jet2",
            "iataCode": "ls",
            "icaoCode": "exs"
        },
        "flight": {
            "number": "478",
            "iataNumber": "ls478",
            "icaoNumber": "exs478"
        }
    },
    {
        "type": "arrival",
        "status": "cancelled",
        "departure": {
            "iataCode": "dub",
            "icaoCode": "eidw",
            "terminal": "2",
            "gate": "333",
            "delay": 24,
            "scheduledTime": "2024-01-21t18:35:00.000",
            "estimatedTime": "2024-01-21t18:59:00.000"
        },
        "arrival": {
            "iataCode": "lba",
            "icaoCode": "egnm",
            "scheduledTime": "2024-01-21t19:55:00.000"
        },
        "airline": {
            "name": "british airways",
            "iataCode": "ba",
            "icaoCode": "baw"
        },
        "flight": {
            "number": "8962",
            "iataNumber": "ba8962",
            "icaoNumber": "baw8962"
        },
        "codeshared": {
            "airline": {
                "name": "aer lingus",
                "iataCode": "ei",
                "icaoCode": "ein"
            },
            "flight": {
                "number": "3394",
                "iataNumber": "ei3394",
                "icaoNumber": "ein3394"
            }
        }
    },
    {
        "type": "arrival",
        "status": "cancelled",
        "departure": {
            "iataCode": "dub",
            "icaoCode": "eidw",
            "terminal": "2",
            "gate": "333",
            "delay": 24,
            "scheduledTime": "2024-01-21t18:35:00.000",
            "estimatedTime": "2024-01-21t18:59:00.000"
        },
        "arrival": {
            "iataCode": "lba",
            "icaoCode": "egnm",
            "scheduledTime": "2024-01-21t19:55:00.000"
        },
        "airline": {
            "name": "aer lingus",
            "iataCode": "ei",
            "icaoCode": "ein"
        },
        "flight": {
            "number": "3394",
            "iataNumber": "ei3394",
            "icaoNumber": "ein3394"
        }
    },
    {
        "type": "arrival",
        "status": "unknown",
        "departure": {
            "iataCode": "bfs",
            "icaoCode": "egaa",
            "delay": 161,
            "scheduledTime": "2024-01-21t19:20:00.000",
            "estimatedTime": "2024-01-21t22:01:00.000"
        },
        "arrival": {
            "iataCode": "lba",
            "icaoCode": "egnm",
            "scheduledTime": "2024-01-21t20:15:00.000"
        },
        "airline": {
            "name": "easyjet",
            "iataCode": "u2",
            "icaoCode": "ezy"
        },
        "flight": {
            "number": "49",
            "iataNumber": "u249",
            "icaoNumber": "ezy49"
        }
    },
    {
        "type": "arrival",
        "status": "landed",
        "departure": {
            "iataCode": "gva",
            "icaoCode": "lsgg",
            "terminal": "2",
            "gate": "c59",
            "delay": 19,
            "scheduledTime": "2024-01-21t20:20:00.000",
            "estimatedTime": "2024-01-21t20:20:00.000",
            "actualTime": "2024-01-21t20:39:00.000",
            "estimatedRunway": "2024-01-21t20:39:00.000",
            "actualRunway": "2024-01-21t20:39:00.000"
        },
        "arrival": {
            "iataCode": "lba",
            "icaoCode": "egnm",
            "scheduledTime": "2024-01-21t21:20:00.000",
            "estimatedTime": "2024-01-21t21:20:00.000",
            "actualTime": "2024-01-21t21:19:00.000",
            "estimatedRunway": "2024-01-21t21:19:00.000",
            "actualRunway": "2024-01-21t21:19:00.000"
        },
        "airline": {
            "name": "jet2",
            "iataCode": "ls",
            "icaoCode": "exs"
        },
        "flight": {
            "number": "288",
            "iataNumber": "ls288",
            "icaoNumber": "exs288"
        }
    },
    {
        "type": "arrival",
        "status": "cancelled",
        "departure": {
            "iataCode": "dub",
            "icaoCode": "eidw",
            "terminal": "1",
            "gate": "108",
            "scheduledTime": "2024-01-21t20:45:00.000",
            "estimatedTime": "2024-01-21t20:45:00.000"
        },
        "arrival": {
            "iataCode": "lba",
            "icaoCode": "egnm",
            "scheduledTime": "2024-01-21t21:45:00.000"
        },
        "airline": {
            "name": "ryanair",
            "iataCode": "fr",
            "icaoCode": "ryr"
        },
        "flight": {
            "number": "457",
            "iataNumber": "fr457",
            "icaoNumber": "ryr457"
        }
    },
    {
        "type": "arrival",
        "status": "scheduled",
        "departure": {
            "iataCode": "wro",
            "icaoCode": "epwr",
            "gate": "19",
            "delay": 34,
            "scheduledTime": "2024-01-21t20:30:00.000",
            "estimatedTime": "2024-01-21t20:41:00.000",
            "actualTime": "2024-01-21t21:03:00.000",
            "estimatedRunway": "2024-01-21t21:03:00.000",
            "actualRunway": "2024-01-21t21:03:00.000"
        },
        "arrival": {
            "iataCode": "lba",
            "icaoCode": "egnm",
            "gate": "9",
            "delay": 39,
            "scheduledTime": "2024-01-21t21:45:00.000",
            "estimatedTime": "2024-01-21t22:23:00.000"
        },
        "airline": {
            "name": "ryanair",
            "iataCode": "fr",
            "icaoCode": "ryr"
        },
        "flight": {
            "number": "4108",
            "iataNumber": "fr4108",
            "icaoNumber": "ryr4108"
        }
    },
    {
        "type": "arrival",
        "status": "scheduled",
        "departure": {
            "iataCode": "krk",
            "icaoCode": "epkk",
            "terminal": "t",
            "gate": "23",
            "delay": 115,
            "scheduledTime": "2024-01-21t20:15:00.000",
            "estimatedTime": "2024-01-21t22:10:00.000"
        },
        "arrival": {
            "iataCode": "lba",
            "icaoCode": "egnm",
            "scheduledTime": "2024-01-21t21:50:00.000"
        },
        "airline": {
            "name": "ryanair",
            "iataCode": "fr",
            "icaoCode": "ryr"
        },
        "flight": {
            "number": "2333",
            "iataNumber": "fr2333",
            "icaoNumber": "ryr2333"
        }
    },
    {
        "type": "arrival",
        "status": "active",
        "departure": {
            "iataCode": "alc",
            "icaoCode": "leal",
            "gate": "50",
            "delay": 12,
            "scheduledTime": "2024-01-21t20:10:00.000",
            "estimatedTime": "2024-01-21t20:21:00.000",
            "actualTime": "2024-01-21t20:22:00.000",
            "estimatedRunway": "2024-01-21t20:22:00.000",
            "actualRunway": "2024-01-21t20:22:00.000"
        },
        "arrival": {
            "iataCode": "lba",
            "icaoCode": "egnm",
            "gate": "b18",
            "delay": 13,
            "scheduledTime": "2024-01-21t22:00:00.000",
            "estimatedTime": "2024-01-21t22:12:00.000"
        },
        "airline": {
            "name": "ryanair",
            "iataCode": "fr",
            "icaoCode": "ryr"
        },
        "flight": {
            "number": "9078",
            "iataNumber": "fr9078",
            "icaoNumber": "ryr9078"
        }
    },
    {
        "type": "arrival",
        "status": "landed",
        "departure": {
            "iataCode": "mla",
            "icaoCode": "lmml",
            "delay": 21,
            "scheduledTime": "2024-01-21t08:00:00.000",
            "estimatedTime": "2024-01-21t08:10:00.000",
            "actualTime": "2024-01-21t08:20:00.000",
            "estimatedRunway": "2024-01-21t08:20:00.000",
            "actualRunway": "2024-01-21t08:20:00.000"
        },
        "arrival": {
            "iataCode": "lba",
            "icaoCode": "egnm",
            "delay": 5,
            "scheduledTime": "2024-01-21t10:46:00.000",
            "estimatedTime": "2024-01-21t10:47:00.000",
            "actualTime": "2024-01-21t10:51:00.000",
            "estimatedRunway": "2024-01-21t10:51:00.000",
            "actualRunway": "2024-01-21t10:51:00.000"
        },
        "airline": {
            "name": "toyo aviation",
            "iataCode": "",
            "icaoCode": "toy"
        },
        "flight": {
            "number": "442",
            "iataNumber": "",
            "icaoNumber": "toy442"
        }
    }
]